{
"skeleton": {
	"hash": "PzUuwZY4E5QmixHp5pjHG7W5xQg",
	"spine": "3.8.0",
	"x": -408.49,
	"y": -4,
	"width": 759.93,
	"height": 1044.03,
	"images": "./images/",
	"audio": "E:/Новая папка/Zombie Soccer/characters/Fatboy/Spine"
},
"bones": [
	{ "name": "root", "color": "fb8a0eff" },
	{ "name": "hip", "parent": "root", "x": -65.8, "y": 347.58, "color": "fb8a0eff" },
	{
		"name": "spine1",
		"parent": "hip",
		"length": 130.45,
		"rotation": 92.05,
		"x": -1.68,
		"y": 21.9,
		"color": "e30efbff"
	},
	{ "name": "spine2", "parent": "spine1", "length": 165.44, "rotation": 0.37, "x": 130.45, "color": "e30efbff" },
	{ "name": "spine3", "parent": "spine2", "length": 131.18, "rotation": -1.06, "x": 165.44, "color": "e30efbff" },
	{
		"name": "head1",
		"parent": "spine3",
		"length": 142.51,
		"rotation": -0.12,
		"x": -151.55,
		"y": -68.72,
		"color": "fb8a0eff"
	},
	{ "name": "head", "parent": "head1", "rotation": -91.24, "x": 23.77, "y": -0.05, "color": "ef0aeaff" },
	{ "name": "head2", "parent": "head1", "length": 199.06, "rotation": 1.42, "x": 142.51, "color": "fb8a0eff" },
	{ "name": "r_eye", "parent": "head2", "rotation": -92.66, "x": 99.62, "y": 27.69, "color": "0c1ff8ff" },
	{ "name": "l_eye", "parent": "head2", "rotation": -92.66, "x": 88.75, "y": -44.02, "color": "30f119ff" },
	{ "name": "l_pupil", "parent": "l_eye", "x": 0.37, "y": 13.53, "color": "30f119ff" },
	{ "name": "r_pupil", "parent": "r_eye", "x": 5.27, "y": 14.78, "color": "0c1ff8ff" },
	{ "name": "r_eyebrow", "parent": "head", "x": -36.28, "y": 281.03, "color": "258af1ff" },
	{ "name": "l_eyebrow", "parent": "head", "x": 18.62, "y": 276.77, "color": "16ec0dff" },
	{ "name": "ear", "parent": "head", "x": -108.62, "y": 205.5, "color": "22a0f9ff" },
	{ "name": "cheeks", "parent": "head2", "rotation": -92.66, "x": 57.49, "y": 62.02, "color": "f59816ff" },
	{ "name": "chin", "parent": "head", "x": 32.46, "y": 29.47, "color": "f86215ff" },
	{ "name": "casc", "parent": "head2", "rotation": -92.66, "x": 246.31, "y": 22.61, "color": "fbaf0aff" },
	{ "name": "nest front", "parent": "casc", "x": -23.33, "y": 31.19, "color": "fbaf0aff" },
	{ "name": "yellow bird", "parent": "casc", "x": -26.88, "y": 49.58, "color": "fbaf0aff" },
	{ "name": "blur bird", "parent": "casc", "x": -60.54, "y": 40.48, "color": "0f83dfff" },
	{
		"name": "hip2",
		"parent": "hip",
		"length": 84.59,
		"rotation": -88.35,
		"x": -0.63,
		"y": -16.5,
		"color": "fb8a0eff"
	},
	{
		"name": "r_thigh",
		"parent": "hip2",
		"length": 230.41,
		"rotation": 36.57,
		"x": 15.32,
		"y": -140.23,
		"color": "0ea2fbff"
	},
	{ "name": "r_knee", "parent": "r_thigh", "length": 110.53, "rotation": -65.03, "x": 230.41, "color": "0ea2fbff" },
	{ "name": "r_feet", "parent": "r_knee", "length": 26.67, "rotation": 64.38, "x": 110.53, "color": "0ea2fbff" },
	{ "name": "r_ball", "parent": "r_feet", "length": 37.46, "rotation": 38.19, "x": 26.67, "color": "0ea2fbff" },
	{
		"name": "l_thigh",
		"parent": "hip2",
		"length": 208.16,
		"rotation": -2.7,
		"x": 6.41,
		"y": 133.85,
		"color": "62fb0eff"
	},
	{ "name": "l_knee", "parent": "l_thigh", "length": 88.67, "rotation": 11.26, "x": 208.16, "color": "62fb0eff" },
	{
		"name": "l_feet",
		"parent": "l_knee",
		"length": 32.2,
		"rotation": -56.57,
		"x": 88.23,
		"y": 0.63,
		"color": "62fb0eff"
	},
	{ "name": "l_ball", "parent": "l_feet", "length": 24.54, "rotation": -37.3, "x": 32.2, "color": "62fb0eff" },
	{
		"name": "r_shoulder",
		"parent": "spine2",
		"length": 255.77,
		"rotation": 174.08,
		"x": 211.06,
		"y": 196.7,
		"color": "0e96fbff"
	},
	{
		"name": "r_forearm",
		"parent": "r_shoulder",
		"length": 194.64,
		"rotation": 63.64,
		"x": 251.8,
		"y": -3.37,
		"color": "0e96fbff"
	},
	{
		"name": "r_palm",
		"parent": "r_forearm",
		"length": 87.55,
		"rotation": 1.6,
		"x": 193.74,
		"y": -0.52,
		"transform": "noRotationOrReflection",
		"color": "0e96fbff"
	},
	{
		"name": "l_shoulder",
		"parent": "spine2",
		"length": 255.19,
		"rotation": -174.11,
		"x": 183.26,
		"y": -207.68,
		"color": "7bfb0eff"
	},
	{ "name": "l_forearm", "parent": "l_shoulder", "length": 189.33, "rotation": -41.13, "x": 255.19, "color": "7bfb0eff" },
	{
		"name": "l_palm",
		"parent": "l_forearm",
		"length": 49.26,
		"rotation": 159.38,
		"x": 189.33,
		"transform": "noRotationOrReflection",
		"color": "7bfb0eff"
	},
	{ "name": "r_ball_target", "parent": "root", "x": -97.72, "y": 10.33, "color": "fb8a0eff" },
	{ "name": "r_leg_target", "parent": "r_ball_target", "x": -16.31, "y": 21.49, "color": "fb8a0eff" },
	{ "name": "l_ball_target", "parent": "root", "x": 56.82, "y": 12.01, "color": "fb8a0eff" },
	{ "name": "l_leg_target", "parent": "l_ball_target", "x": 23.05, "y": 20.83, "color": "fb8a0eff" },
	{ "name": "automat_main", "parent": "hip", "x": 82.05, "y": 85.16, "color": "fb8a0eff" },
	{
		"name": "automat",
		"parent": "automat_main",
		"length": 268.49,
		"rotation": 164.45,
		"x": -16.93,
		"y": 5.78,
		"color": "fb8a0eff"
	},
	{ "name": "r_arm_target", "parent": "automat", "rotation": -164.45, "x": 135.52, "y": 105.55, "color": "fb8a0eff" },
	{
		"name": "automat1",
		"parent": "automat_main",
		"length": 263.59,
		"rotation": -16.21,
		"x": 26.58,
		"y": -4.51,
		"color": "fb8a0eff"
	},
	{
		"name": "automat_handle",
		"parent": "automat_main",
		"length": 126.16,
		"rotation": -98.63,
		"x": -0.05,
		"y": -56.91,
		"color": "fb8a0eff"
	},
	{ "name": "r_armtarget", "parent": "automat_handle", "rotation": 98.47, "x": 74.84, "y": 24.75, "color": "fb8a0eff" },
	{ "name": "fat", "parent": "hip", "x": -26.8, "y": -48.02, "color": "fb8a0eff" },
	{ "name": "hair", "parent": "head2", "rotation": -92.66, "x": 203.02, "y": -16.17, "color": "ef0aeaff" },
	{
		"name": "yellow bird2",
		"parent": "yellow bird",
		"length": 14.64,
		"rotation": 94.5,
		"x": -0.98,
		"y": 5.35,
		"color": "fbaf0aff"
	},
	{
		"name": "yellow bird3",
		"parent": "yellow bird2",
		"length": 21.52,
		"rotation": -22.24,
		"x": 14.5,
		"y": 0.34,
		"color": "fbaf0aff"
	},
	{
		"name": "yellow bird4",
		"parent": "yellow bird3",
		"length": 19.65,
		"rotation": 11.03,
		"x": 21.47,
		"y": 0.16,
		"color": "fbaf0aff"
	},
	{
		"name": "yellow bird5",
		"parent": "yellow bird3",
		"length": 12.74,
		"rotation": -40.41,
		"x": 20.94,
		"y": -1.39,
		"color": "fbaf0aff"
	},
	{
		"name": "yellow bird6",
		"parent": "yellow bird2",
		"length": 19.17,
		"rotation": -70.78,
		"x": 4.2,
		"y": -0.99,
		"color": "fbaf0aff"
	},
	{
		"name": "blur bird2",
		"parent": "blur bird",
		"length": 19.52,
		"rotation": 90,
		"x": -1.92,
		"y": 5.27,
		"color": "0f83dfff"
	},
	{ "name": "blur bird3", "parent": "blur bird2", "length": 20.21, "rotation": 38.08, "x": 19.52, "color": "0f83dfff" },
	{ "name": "blur bird4", "parent": "blur bird3", "length": 15.89, "rotation": 5.67, "x": 20.21, "color": "0f83dfff" },
	{
		"name": "blur bird5",
		"parent": "blur bird3",
		"length": 11.42,
		"rotation": 39.48,
		"x": 19.17,
		"y": 3.73,
		"color": "0f83dfff"
	},
	{
		"name": "blur bird6",
		"parent": "blur bird2",
		"length": 17.63,
		"rotation": -43.49,
		"x": 15.58,
		"y": -2.46,
		"color": "0f83dfff"
	},
	{
		"name": "blur bird7",
		"parent": "blur bird2",
		"length": 14.85,
		"rotation": 73.97,
		"x": 12.3,
		"y": 3.61,
		"color": "0f83dfff"
	},
	{
		"name": "yellow bird7",
		"parent": "yellow bird2",
		"length": 13.34,
		"rotation": 58.13,
		"x": 1.79,
		"y": 7.23,
		"color": "fbaf0aff"
	},
	{ "name": "mouth", "parent": "head", "x": 21.57, "y": 111.06, "color": "ef0aeaff" }
],
"slots": [
	{ "name": "fat", "bone": "fat", "attachment": "fat" },
	{ "name": "legs", "bone": "root", "attachment": "legs" },
	{ "name": "body", "bone": "root", "attachment": "body" },
	{ "name": "automat", "bone": "automat", "attachment": "automat" },
	{ "name": "r_arm", "bone": "root", "attachment": "r_arm" },
	{ "name": "l_arm", "bone": "root", "attachment": "l_arm" },
	{ "name": "automat1", "bone": "automat1", "attachment": "automat1" },
	{ "name": "head", "bone": "head", "attachment": "head" },
	{ "name": "hair", "bone": "hair", "attachment": "hair" },
	{ "name": "casc", "bone": "casc", "attachment": "casc" },
	{ "name": "nest back", "bone": "casc", "attachment": "nest back" },
	{ "name": "blur bird", "bone": "blur bird", "attachment": "blur bird" },
	{ "name": "yellow bird", "bone": "yellow bird", "attachment": "yellow bird" },
	{ "name": "nest front", "bone": "nest front", "attachment": "nest front" },
	{ "name": "ear", "bone": "ear", "attachment": "ear" },
	{ "name": "chin", "bone": "chin", "attachment": "chin" },
	{ "name": "mouth", "bone": "mouth", "attachment": "mouth" },
	{ "name": "cheeks", "bone": "cheeks", "attachment": "cheeks" },
	{ "name": "nose", "bone": "head", "attachment": "nose" },
	{ "name": "r_eye", "bone": "r_eye", "attachment": "r_eye" },
	{ "name": "r_pupil", "bone": "r_pupil", "attachment": "r_pupil" },
	{ "name": "l_eye", "bone": "l_eye", "attachment": "l_eye" },
	{ "name": "l_pupil", "bone": "l_pupil", "attachment": "l_pupil" },
	{ "name": "l_eyebrow", "bone": "l_eyebrow", "attachment": "l_eyebrow" },
	{ "name": "r_eyebrow", "bone": "r_eyebrow", "attachment": "r_eyebrow" }
],
"ik": [
	{
		"name": "l_arm_target",
		"order": 5,
		"bones": [ "l_shoulder", "l_forearm" ],
		"target": "r_armtarget",
		"bendPositive": false,
		"stretch": true
	},
	{
		"name": "l_ball_target",
		"order": 3,
		"bones": [ "l_feet" ],
		"target": "l_ball_target"
	},
	{
		"name": "l_leg_target",
		"order": 2,
		"bones": [ "l_thigh", "l_knee" ],
		"target": "l_leg_target",
		"stretch": true
	},
	{
		"name": "r_arm_target",
		"order": 4,
		"bones": [ "r_shoulder", "r_forearm" ],
		"target": "r_arm_target",
		"stretch": true
	},
	{
		"name": "r_ball_target",
		"order": 1,
		"bones": [ "r_feet" ],
		"target": "r_ball_target"
	},
	{
		"name": "r_leg_target",
		"bones": [ "r_thigh", "r_knee" ],
		"target": "r_leg_target",
		"bendPositive": false,
		"stretch": true
	}
],
"skins": [
	{
		"name": "default",
		"attachments": {
			"automat1": {
				"automat1": { "x": 145.62, "y": 17.11, "rotation": 16.21, "width": 328, "height": 186 }
			},
			"r_pupil": {
				"r_pupil": { "x": 0.35, "y": -0.71, "width": 12, "height": 12 }
			},
			"mouth": {
				"mouth": { "x": -18.33, "y": 11.44, "width": 113, "height": 109 }
			},
			"l_arm": {
				"l_arm": {
					"type": "mesh",
					"uvs": [ 0.59664, 0, 0.87988, 0.13165, 0.93538, 0.23601, 1, 0.35754, 1, 0.47063, 0.9576, 0.54761, 0.91762, 0.62019, 0.87666, 0.69457, 0.85301, 0.73749, 0.70786, 0.82024, 0.54136, 0.91515, 0.45692, 0.96328, 0.39702, 0.99742, 0.34278, 0.99754, 0.29505, 0.99765, 0.06293, 0.99816, 0.00634, 0.99428, 0.01695, 0.82312, 0.12545, 0.8118, 0.19282, 0.80478, 0.25192, 0.79862, 0.31015, 0.79254, 0.37505, 0.78578, 0.46208, 0.7767, 0.52149, 0.66812, 0.55277, 0.61095, 0.51739, 0.5356, 0.47777, 0.4512, 0.43158, 0.35281, 0.39706, 0.27928, 0.35749, 0.195, 0.51833, 0 ],
					"triangles": [ 16, 17, 15, 15, 18, 14, 15, 17, 18, 18, 19, 14, 14, 19, 13, 19, 20, 13, 13, 20, 12, 12, 20, 11, 11, 20, 21, 11, 21, 10, 10, 21, 22, 22, 23, 10, 10, 23, 9, 8, 9, 24, 9, 23, 24, 8, 24, 7, 24, 25, 7, 7, 25, 6, 6, 25, 5, 25, 26, 5, 5, 26, 4, 26, 27, 4, 27, 3, 4, 27, 28, 3, 28, 2, 3, 28, 29, 2, 2, 29, 1, 29, 30, 1, 30, 0, 1, 30, 31, 0 ],
					"vertices": [ 1, 33, -42.64, 7.55, 1, 1, 33, 32.05, 63.47, 1, 1, 33, 85.64, 68.81, 1, 1, 33, 148.05, 75.03, 1, 1, 33, 204.13, 66.96, 1, 2, 33, 240.9, 51.68, 0.95575, 34, -44.73, 29.56, 0.04425, 2, 33, 275.56, 37.27, 0.42724, 34, -9.14, 41.49, 0.57276, 2, 33, 311.08, 22.51, 0.01703, 34, 27.34, 53.7, 0.98297, 1, 34, 48.39, 60.75, 1, 1, 34, 101.56, 54.86, 1, 2, 34, 162.56, 48.09, 0.99974, 35, -52.68, -15.95, 2.6E-4, 2, 34, 193.49, 44.67, 0.86693, 35, -42.76, 13.55, 0.13307, 2, 34, 215.43, 42.23, 0.65326, 35, -35.73, 34.47, 0.34674, 2, 34, 222.34, 31.65, 0.51828, 35, -23.92, 38.98, 0.48172, 2, 34, 228.43, 22.34, 0.3446, 35, -13.53, 42.95, 0.6554, 1, 35, 37, 62.24, 1, 1, 35, 50.02, 65.06, 1, 2, 34, 190.18, -79.55, 0.00456, 35, 77.91, -16.07, 0.99544, 2, 34, 171.69, -61.39, 0.10924, 35, 56.25, -30.28, 0.89076, 2, 34, 160.21, -50.12, 0.3235, 35, 42.79, -39.1, 0.6765, 2, 34, 150.15, -40.24, 0.57812, 35, 30.99, -46.84, 0.42188, 2, 34, 140.22, -30.49, 0.80552, 35, 19.37, -54.47, 0.19448, 2, 34, 129.17, -19.64, 0.95312, 35, 6.41, -62.97, 0.04688, 2, 34, 114.34, -5.08, 0.99962, 35, -10.97, -74.36, 3.8E-4, 2, 33, 286.17, -57.5, 0.00817, 34, 61.14, -22.99, 0.99183, 2, 33, 258.86, -46.21, 0.24207, 34, 33.13, -32.42, 0.75793, 2, 33, 220.32, -48.98, 0.85631, 34, 5.9, -59.84, 0.14369, 2, 33, 177.15, -52.09, 0.99809, 34, -24.59, -90.55, 0.00191, 1, 33, 126.83, -55.72, 1, 1, 33, 89.21, -58.43, 1, 1, 33, 46.11, -61.53, 1, 1, 33, -45.24, -10.51, 1 ],
					"hull": 32,
					"edges": [ 0, 62, 0, 2, 6, 8, 30, 32, 32, 34, 60, 62, 60, 2, 58, 60, 2, 4, 4, 6, 58, 4, 56, 58, 56, 6, 54, 56, 54, 8, 50, 52, 52, 54, 8, 10, 52, 10, 10, 12, 50, 12, 46, 48, 48, 50, 12, 14, 14, 16, 48, 14, 16, 18, 46, 18, 44, 46, 18, 20, 44, 20, 40, 24, 34, 36, 28, 30, 36, 28, 40, 42, 42, 44, 20, 22, 22, 24, 42, 22, 36, 38, 38, 40, 24, 26, 26, 28, 38, 26 ],
					"width": 233,
					"height": 501
				}
			},
			"chin": {
				"chin": { "x": -6.22, "y": -0.47, "width": 69, "height": 82 }
			},
			"r_arm": {
				"r_arm": {
					"type": "mesh",
					"uvs": [ 0.5835, 0.13423, 0.5366, 0.21516, 0.48196, 0.30943, 0.44472, 0.37369, 0.4224, 0.41221, 0.35689, 0.42192, 0.40576, 0.50773, 0.44892, 0.58352, 0.47263, 0.62515, 0.5104, 0.69148, 0.58475, 0.82202, 0.64217, 0.85335, 0.69833, 0.8391, 0.78906, 0.81608, 0.8561, 0.79907, 0.99778, 0.88316, 0.85939, 1, 0.85619, 1, 0.78837, 0.9836, 0.66846, 0.9546, 0.6126, 0.94109, 0.52176, 0.91912, 0.45044, 0.90188, 0.23571, 0.78785, 0.16877, 0.69003, 0.12513, 0.62625, 0.09659, 0.58454, 0, 0.44339, 0, 0.36639, 0, 0.26378, 0.02006, 0.22471, 0.06996, 0.1275, 0.13541, 0, 0.22771, 0, 0.453, 0.01527 ],
					"triangles": [ 20, 11, 19, 18, 12, 13, 19, 12, 18, 16, 17, 14, 13, 14, 17, 18, 13, 17, 15, 16, 14, 24, 25, 7, 24, 7, 8, 23, 24, 8, 23, 8, 9, 22, 23, 9, 22, 9, 10, 21, 22, 10, 21, 10, 11, 20, 21, 11, 19, 11, 12, 1, 34, 0, 33, 34, 1, 31, 32, 33, 1, 31, 33, 2, 31, 1, 30, 31, 2, 28, 29, 30, 3, 28, 30, 2, 3, 30, 3, 5, 28, 4, 5, 3, 27, 28, 5, 26, 27, 5, 26, 5, 6, 25, 26, 6, 25, 6, 7 ],
					"vertices": [ 1, 30, 8.26, 117.41, 1, 1, 30, 44.55, 101.71, 1, 1, 30, 86.82, 83.42, 1, 1, 30, 115.64, 70.95, 1, 1, 30, 132.91, 63.47, 1, 2, 30, 138.75, 38.64, 0.997, 31, -11.65, 120.04, 0.003, 2, 30, 174.79, 59.77, 0.85917, 31, 23.12, 96.87, 0.14083, 2, 30, 206.62, 78.44, 0.48871, 31, 53.82, 76.4, 0.51129, 2, 30, 224.11, 88.69, 0.26194, 31, 70.69, 65.16, 0.73806, 2, 30, 251.96, 105.03, 0.04731, 31, 97.56, 47.25, 0.95269, 1, 31, 150.45, 12, 1, 1, 31, 176.35, 11.06, 1, 2, 31, 192.03, 27.1, 0.62514, 32, 12.86, 24.5, 0.37486, 2, 31, 217.37, 53.03, 0.04324, 32, 47.97, 33.54, 0.95676, 2, 31, 236.09, 72.19, 0.0018, 32, 73.91, 40.22, 0.9982, 1, 32, 127.27, 2.14, 1, 1, 32, 72.73, -47.19, 1, 1, 32, 71.5, -47.15, 1, 1, 32, 45.67, -39.29, 1, 1, 32, 0, -25.4, 1, 2, 31, 185.35, -27.74, 0.31704, 32, -21.29, -18.93, 0.68296, 2, 31, 150.3, -36.67, 0.92076, 32, -55.88, -8.4, 0.07924, 3, 30, 344.78, 87.95, 2.0E-5, 31, 122.79, -43.69, 0.99374, 32, -83.05, -0.14, 0.00624, 2, 30, 300.6, 2.46, 0.58504, 31, 26.59, -41.33, 0.41496, 2, 30, 259.79, -25.93, 0.19553, 31, -16.79, -17.05, 0.80447, 2, 30, 233.19, -44.44, 0.30806, 31, -45.07, -1.22, 0.69194, 2, 30, 215.79, -56.55, 0.58024, 31, -63.57, 9.14, 0.41976, 2, 30, 156.9, -97.52, 0.91787, 31, -126.16, 44.18, 0.08213, 2, 30, 123.48, -99.67, 0.96148, 31, -142.72, 73.3, 0.03852, 2, 30, 78.93, -102.55, 0.9908, 31, -164.78, 112.1, 0.0092, 2, 30, 61.48, -95.96, 0.99542, 31, -166.49, 130.68, 0.00458, 2, 30, 18.04, -79.56, 0.99993, 31, -170.73, 176.91, 7.0E-5, 1, 30, -38.92, -58.06, 1, 1, 30, -41.21, -22.69, 1, 1, 30, -40.16, 64.07, 1 ],
					"hull": 35,
					"edges": [ 0, 68, 8, 10, 20, 22, 28, 30, 30, 32, 32, 34, 44, 46, 64, 66, 66, 68, 52, 54, 10, 12, 52, 12, 46, 48, 48, 16, 16, 18, 18, 20, 46, 18, 48, 50, 50, 52, 12, 14, 14, 16, 50, 14, 40, 22, 38, 40, 22, 24, 38, 24, 40, 42, 42, 44, 42, 20, 34, 36, 36, 38, 24, 26, 26, 28, 36, 26, 62, 64, 0, 2, 62, 2, 58, 60, 60, 62, 2, 4, 60, 4, 54, 56, 56, 58, 4, 6, 6, 8, 56, 6 ],
					"width": 384,
					"height": 435
				}
			},
			"automat": {
				"automat": {
					"type": "mesh",
					"uvs": [ 0.35849, 0.07107, 0.52652, 0.12077, 0.61291, 0.1778, 0.66231, 0.21041, 0.69846, 0.24574, 0.75896, 0.24587, 0.83372, 0.24602, 0.89154, 0.27124, 0.94646, 0.2952, 0.96629, 0.30384, 1, 0.31844, 0.93347, 0.43637, 0.95193, 0.49333, 0.95751, 0.56413, 0.96247, 0.62706, 0.90347, 0.64655, 0.89657, 0.67666, 0.88665, 0.71993, 0.8757, 0.7677, 0.86228, 0.82626, 0.85637, 0.85207, 0.86984, 0.91853, 0.88081, 0.97267, 0.842, 0.99737, 0.80055, 0.99792, 0.73787, 0.93526, 0.74517, 0.87137, 0.75175, 0.81389, 0.75943, 0.74673, 0.76694, 0.68107, 0.77219, 0.63521, 0.81389, 0.61349, 0.77087, 0.61263, 0.73129, 0.61183, 0.69985, 0.58163, 0.6643, 0.61187, 0.63914, 0.64639, 0.56076, 0.77533, 0.53879, 0.79489, 0.50575, 0.75294, 0.48083, 0.72132, 0.52428, 0.60215, 0.55217, 0.56594, 0.56901, 0.54406, 0.51581, 0.56703, 0.48456, 0.55859, 0.43131, 0.5462, 0.33301, 0.52333, 0.22352, 0.49785, 0.09217, 0.39006, 0, 0.25634, 0, 0.22466, 0.05319, 0.13524, 0.14539, 0.08989, 0.76042, 0.5078, 0.80599, 0.51328, 0.85216, 0.52161, 0.74519, 0.56221, 0.7883, 0.56333, 0.83149, 0.57124, 0.64571, 0.52953, 0.62874, 0.56121, 0.61088, 0.58999, 0.57829, 0.62295 ],
					"triangles": [ 59, 55, 56, 56, 12, 13, 12, 56, 11, 56, 8, 11, 55, 7, 56, 11, 9, 10, 11, 8, 9, 8, 56, 7, 23, 24, 21, 23, 21, 22, 21, 24, 25, 21, 26, 20, 21, 25, 26, 26, 27, 20, 20, 27, 19, 18, 19, 28, 19, 27, 28, 18, 28, 17, 28, 29, 17, 17, 29, 16, 29, 30, 16, 30, 31, 16, 16, 31, 15, 31, 59, 15, 15, 59, 14, 14, 59, 13, 59, 56, 13, 32, 58, 31, 31, 58, 59, 38, 39, 37, 37, 63, 36, 37, 39, 63, 39, 40, 63, 40, 41, 63, 63, 62, 36, 36, 62, 35, 41, 42, 63, 63, 42, 62, 33, 57, 32, 32, 57, 58, 62, 61, 35, 35, 61, 34, 33, 34, 57, 42, 43, 62, 62, 43, 61, 61, 60, 34, 34, 60, 57, 58, 55, 59, 44, 3, 43, 57, 54, 58, 58, 54, 55, 57, 60, 54, 61, 43, 60, 45, 3, 44, 2, 45, 46, 43, 4, 60, 5, 60, 4, 5, 54, 60, 1, 2, 46, 4, 43, 3, 45, 2, 3, 46, 47, 1, 47, 0, 1, 47, 48, 0, 7, 55, 6, 6, 55, 54, 54, 5, 6, 48, 49, 0, 0, 49, 53, 50, 52, 49, 49, 52, 53, 50, 51, 52 ],
					"vertices": [ 1, 41, 201.37, -91.58, 1, 1, 41, 135.74, -90.75, 1, 1, 41, 98.87, -79.11, 1, 2, 41, 77.79, -72.45, 0.99667, 40, -72.44, 96.43, 0.00333, 2, 41, 61.23, -63.49, 0.97346, 40, -58.89, 83.36, 0.02654, 2, 41, 39.35, -69.53, 0.87984, 40, -36.2, 83.31, 0.12016, 2, 41, 12.33, -76.99, 0.69271, 40, -8.16, 83.26, 0.30729, 2, 41, -11.06, -73.82, 0.48464, 40, 13.52, 73.92, 0.51536, 2, 41, -33.28, -70.8, 0.28709, 40, 34.12, 65.06, 0.71291, 2, 41, -41.3, -69.71, 0.24162, 40, 41.55, 61.86, 0.75838, 2, 41, -54.93, -67.89, 0.21368, 40, 54.19, 56.46, 0.78632, 3, 41, -42.59, -19.17, 0.05114, 44, -73.29, 18.7, 0.03037, 40, 29.24, 12.83, 0.91849, 2, 44, -53.46, 28.65, 0.2108, 40, 36.17, -8.25, 0.7892, 2, 44, -27.86, 34.58, 0.54698, 40, 38.26, -34.44, 0.45302, 2, 44, -5.11, 39.85, 0.74961, 40, 40.12, -57.73, 0.25039, 2, 44, 5.28, 19.03, 0.92047, 40, 17.99, -64.94, 0.07953, 2, 44, 16.69, 18.11, 0.99004, 40, 15.41, -76.08, 0.00996, 1, 44, 33.07, 16.8, 1, 1, 44, 51.15, 15.34, 1, 1, 44, 73.33, 13.55, 1, 1, 44, 83.1, 12.77, 1, 1, 44, 106.68, 21.39, 1, 1, 44, 125.89, 28.41, 1, 1, 44, 137.07, 15.36, 1, 1, 44, 139.56, 0.02, 1, 1, 44, 120.09, -26.65, 1, 1, 44, 96.31, -27.42, 1, 1, 44, 74.91, -28.12, 1, 1, 44, 49.91, -28.93, 1, 1, 44, 25.46, -29.72, 1, 2, 41, -4.05, 67.92, 0.01217, 44, 8.39, -30.28, 0.98783, 3, 41, -16.96, 55.99, 0.14455, 44, -1.86, -15.99, 0.82308, 40, -15.6, -52.71, 0.03237, 3, 41, -1.33, 60, 0.51992, 44, 0.2, -32, 0.45157, 40, -31.73, -52.39, 0.02851, 3, 41, 13.05, 63.7, 0.68787, 44, 2.09, -46.72, 0.30533, 40, -46.57, -52.09, 0.0068, 2, 41, 27.4, 56.09, 0.85158, 44, -7.22, -60.03, 0.14842, 2, 41, 37.25, 70.45, 0.94883, 44, 5.81, -71.57, 0.05117, 2, 41, 42.91, 85.28, 0.97786, 44, 19.83, -79.02, 0.02214, 2, 41, 58.44, 139.12, 0.99991, 44, 71.35, -101.06, 9.0E-5, 1, 41, 64.43, 148.31, 1, 1, 41, 80.53, 136.68, 1, 2, 41, 92.67, 127.91, 0.99997, 44, 56, -133.65, 3.0E-5, 2, 41, 88.8, 81.06, 0.99291, 44, 9.99, -124.03, 0.00709, 2, 41, 82.31, 65.35, 0.98874, 44, -4.8, -115.66, 0.01126, 2, 41, 78.4, 55.86, 0.99038, 44, -13.74, -110.61, 0.00962, 2, 41, 95.34, 69.39, 0.99896, 44, -2.39, -129.09, 0.00104, 2, 41, 107.47, 69.53, 0.99976, 44, -3.76, -141.14, 2.4E-4, 1, 41, 127.93, 70.46, 1, 1, 41, 165.72, 72.19, 1, 1, 41, 207.8, 74.12, 1, 1, 41, 265.94, 48.91, 1, 1, 41, 312.51, 10.51, 1, 1, 41, 315.65, -0.79, 1, 1, 41, 305.3, -38.01, 1, 1, 41, 276.49, -63.44, 1, 3, 41, 12.84, 23.69, 0.85322, 44, -37.59, -41.59, 0.11786, 40, -35.65, -13.6, 0.02892, 3, 41, -4.16, 21.06, 0.58981, 44, -38.1, -24.39, 0.18099, 40, -18.56, -15.63, 0.2292, 3, 41, -21.67, 19.39, 0.15317, 44, -37.6, -6.81, 0.26072, 40, -1.25, -18.71, 0.58611, 3, 41, 12.95, 44.61, 0.72668, 44, -16.83, -44.27, 0.25358, 40, -41.36, -33.73, 0.01974, 3, 41, -2.74, 40.68, 0.50495, 44, -18.81, -28.22, 0.3963, 40, -25.2, -34.15, 0.09875, 3, 41, -19.13, 39.16, 0.20983, 44, -18.3, -11.77, 0.58187, 40, -9, -37.08, 0.2083, 2, 41, 52.13, 42.97, 0.96142, 44, -23.29, -82.95, 0.03858, 2, 41, 55.12, 55.97, 0.96478, 44, -10.76, -87.52, 0.03522, 2, 41, 58.72, 68.02, 0.97475, 44, 0.75, -92.58, 0.02525, 2, 41, 67.22, 83.05, 0.98829, 44, 14.62, -102.87, 0.01171 ],
					"hull": 54,
					"edges": [ 0, 2, 6, 8, 18, 20, 22, 24, 44, 46, 46, 48, 48, 50, 74, 76, 96, 98, 98, 100, 100, 102, 102, 104, 104, 106, 106, 0, 20, 22, 28, 30, 86, 88, 88, 90, 68, 70, 80, 82, 70, 72, 72, 74, 82, 84, 84, 86, 66, 68, 60, 62, 30, 32, 60, 32, 58, 60, 32, 34, 58, 34, 56, 58, 34, 36, 56, 36, 54, 56, 36, 38, 38, 40, 54, 38, 50, 52, 52, 54, 52, 40, 40, 42, 42, 44, 50, 42, 62, 30, 12, 14, 62, 64, 64, 66, 14, 16, 16, 18, 12, 108, 14, 110, 108, 110, 16, 112, 110, 112, 24, 26, 26, 28, 112, 26, 66, 114, 114, 108, 64, 116, 116, 110, 114, 116, 62, 118, 118, 112, 116, 118, 118, 28, 114, 68, 6, 88, 2, 4, 4, 6, 90, 92, 4, 92, 92, 94, 94, 96, 2, 94, 0, 96, 8, 86, 8, 10, 10, 12, 86, 120, 120, 108, 10, 120, 68, 122, 122, 86, 120, 122, 70, 124, 124, 84, 122, 124, 72, 126, 126, 82, 124, 126, 76, 78, 78, 80, 126, 78 ],
					"width": 375,
					"height": 370
				}
			},
			"blur bird": {
				"blur bird": {
					"type": "mesh",
					"uvs": [ 0.30347, 0.06514, 0.35418, 0.09149, 0.38436, 0.10717, 0.55842, 0.11105, 0.66216, 0.11337, 0.77453, 0.18721, 0.81389, 0.21308, 0.82279, 0.34583, 0.8791, 0.31343, 0.97966, 0.25558, 0.98059, 0.37723, 0.90462, 0.49464, 0.81294, 0.63632, 0.83205, 0.73829, 0.8367, 0.87415, 0.80467, 0.91918, 0.60443, 0.98483, 0.54019, 0.985, 0.47863, 0.96989, 0.45813, 0.89499, 0.45804, 0.86906, 0.45785, 0.81407, 0.45753, 0.72235, 0.32337, 0.62394, 0.2348, 0.55897, 0.18338, 0.49202, 0.28794, 0.49178, 0.33162, 0.49168, 0.26698, 0.39499, 0.24573, 0.36321, 0.22367, 0.33021, 0.19141, 0.31509, 0.1382, 0.29014, 0, 0.22535, 0.18631, 0.20529, 0, 0.01167, 0.30398, 0.55161, 0.38265, 0.58516, 0.81848, 0.47307, 0.89472, 0.42433, 0.4216, 0.46496, 0.48111, 0.55984, 0.51861, 0.70756, 0.49698, 0.77567, 0.73331, 0.3724, 0.73008, 0.49581, 0.75009, 0.65153, 0.3706, 0.35258, 0.52137, 0.43534, 0.57631, 0.53536, 0.60598, 0.68642, 0.58967, 0.78738 ],
					"triangles": [ 49, 45, 46, 50, 49, 46, 41, 49, 50, 42, 41, 50, 46, 12, 13, 43, 22, 42, 51, 42, 50, 43, 42, 51, 13, 51, 50, 13, 50, 46, 21, 22, 43, 21, 43, 51, 20, 21, 51, 51, 13, 14, 19, 20, 51, 15, 51, 14, 19, 17, 18, 51, 16, 19, 15, 16, 51, 16, 17, 19, 27, 28, 40, 36, 26, 27, 25, 26, 36, 24, 25, 36, 41, 40, 48, 41, 48, 49, 37, 27, 40, 37, 40, 41, 36, 27, 37, 23, 36, 37, 24, 36, 23, 37, 41, 42, 22, 23, 37, 42, 22, 37, 44, 6, 7, 39, 8, 9, 10, 39, 9, 7, 8, 39, 38, 44, 7, 38, 7, 39, 11, 39, 10, 38, 39, 11, 45, 48, 44, 45, 44, 38, 49, 48, 45, 12, 45, 38, 12, 38, 11, 46, 45, 12, 5, 47, 3, 5, 3, 4, 3, 47, 29, 44, 47, 5, 44, 5, 6, 48, 47, 44, 40, 47, 48, 32, 33, 34, 1, 31, 34, 32, 34, 31, 30, 31, 2, 2, 29, 30, 28, 29, 47, 28, 47, 40, 34, 35, 0, 34, 0, 1, 1, 2, 31, 3, 29, 2 ],
					"vertices": [ 2, 55, 10.05, -5.26, 0.99522, 54, 30.73, -4.24, 0.00478, 3, 55, 7.13, -5.83, 0.9405, 54, 27.88, -5.1, 0.05856, 57, 10.29, 31.32, 9.4E-4, 3, 55, 5.39, -6.18, 0.83033, 54, 26.18, -5.61, 0.1659, 57, 10.55, 29.57, 0.00378, 3, 55, -0.57, -12.04, 0.23151, 54, 20.83, -12.03, 0.71019, 57, 16.12, 23.34, 0.0583, 3, 55, -4.12, -15.53, 0.10199, 54, 17.64, -15.86, 0.78532, 57, 19.44, 19.62, 0.1127, 3, 55, -11.32, -16.11, 0.02079, 54, 10.54, -17.15, 0.73637, 57, 19.67, 12.4, 0.24285, 3, 55, -13.84, -16.31, 0.01003, 54, 8.05, -17.6, 0.69895, 57, 19.75, 9.88, 0.29102, 2, 54, 0.99, -12.61, 0.20576, 57, 13.78, 3.63, 0.79424, 2, 54, 0.98, -16.04, 0.01068, 57, 17.17, 3.11, 0.98932, 1, 57, 23.22, 2.2, 1, 1, 57, 17.51, -3.27, 1, 2, 57, 9.47, -5.88, 0.99985, 53, 18.4, -13.24, 1.5E-4, 2, 57, -0.24, -9.03, 0.46702, 53, 9.19, -8.84, 0.53298, 2, 57, -4.42, -14.25, 0.08278, 53, 2.57, -9.76, 0.91722, 2, 57, -10.67, -20.49, 0.00118, 53, -6.27, -9.98, 0.99882, 1, 53, -9.19, -8.45, 1, 1, 53, -13.46, 1.17, 1, 1, 53, -13.47, 4.25, 1, 1, 53, -12.49, 7.21, 1, 2, 58, -1.1, 20.41, 0.0032, 53, -7.62, 8.19, 0.9968, 2, 58, -0.63, 18.79, 0.01005, 53, -5.94, 8.19, 0.98995, 2, 58, 0.37, 15.36, 0.05525, 53, -2.36, 8.2, 0.94475, 2, 58, 2.03, 9.63, 0.42845, 53, 3.6, 8.22, 0.57155, 2, 58, 9.98, 5.26, 0.99452, 53, 10, 14.66, 0.00548, 1, 58, 15.24, 2.38, 1, 1, 58, 18.81, -1.12, 1, 3, 56, -1.39, 13.74, 0.01404, 54, 9.36, 13.45, 0.01768, 58, 13.99, -2.52, 0.96828, 4, 56, -3.44, 13.28, 0.08347, 54, 8.07, 11.79, 0.11356, 58, 11.98, -3.11, 0.80268, 53, 18.59, 14.26, 2.9E-4, 3, 56, 0.94, 7.82, 0.65048, 54, 14.93, 10.36, 0.18372, 58, 16.7, -8.29, 0.1658, 3, 56, 2.38, 6.02, 0.83173, 54, 17.19, 9.89, 0.08768, 58, 18.25, -9.99, 0.08059, 3, 56, 3.88, 4.15, 0.96359, 54, 19.53, 9.4, 0.01209, 58, 19.86, -11.76, 0.02432, 2, 56, 5.6, 3.52, 0.994, 58, 21.62, -12.28, 0.006, 2, 56, 8.45, 2.49, 0.99995, 58, 24.52, -13.13, 5.0E-5, 2, 55, 12.6, 12.46, 1.0E-5, 56, 15.83, -0.19, 0.99999, 2, 55, 7.36, 5.1, 0.42199, 56, 7.38, -3.39, 0.57801, 1, 55, 22.63, 2.86, 1, 1, 58, 12.18, 1, 1, 2, 58, 7.95, 2.06, 0.99883, 53, 12.52, 11.81, 0.00117, 1, 57, 7.64, -1.92, 1, 1, 57, 12.46, -2.39, 1, 4, 56, -7.28, 10.66, 0.09215, 54, 6.77, 7.32, 0.38228, 58, 8.31, -5.97, 0.50458, 53, 20.33, 9.94, 0.02099, 4, 56, -11.4, 16.06, 6.7E-4, 54, 0.16, 8.88, 0.02205, 58, 3.86, -0.83, 0.95298, 53, 14.16, 7.09, 0.0243, 2, 58, -0.52, 7.9, 0.33787, 53, 4.56, 5.29, 0.66213, 2, 58, -0.75, 12.44, 0.12026, 53, 0.13, 6.32, 0.87974, 2, 54, 2.28, -8.16, 0.44619, 57, 9.57, 5.55, 0.55381, 3, 54, -3.94, -3.1, 0.00609, 57, 3.65, 0.15, 0.98871, 53, 18.33, -4.86, 0.0052, 2, 57, -3.03, -7.52, 0.29246, 53, 8.2, -5.83, 0.70754, 3, 56, -3.32, 4.05, 0.44239, 54, 14.03, 4.75, 0.47947, 58, 12.68, -12.31, 0.07814, 4, 56, -11.55, 7.75, 0.01169, 54, 5.34, 2.37, 0.83748, 58, 4.24, -9.14, 0.11301, 53, 22.26, 5.15, 0.03782, 3, 54, -1.41, 4.3, 0.05678, 58, -0.1, -3.62, 0.32983, 53, 15.76, 2.52, 0.61339, 2, 58, -4.18, 5.42, 0.05986, 53, 5.94, 1.09, 0.94014, 2, 58, -5.24, 11.94, 0.01657, 53, -0.63, 1.88, 0.98343 ],
					"hull": 36,
					"edges": [ 0, 70, 12, 14, 18, 20, 24, 26, 26, 28, 28, 30, 30, 32, 32, 34, 34, 36, 36, 38, 48, 50, 66, 68, 68, 70, 68, 0, 64, 66, 68, 64, 60, 4, 0, 2, 2, 4, 60, 62, 62, 64, 2, 62, 50, 52, 52, 54, 44, 46, 46, 48, 14, 16, 16, 18, 20, 22, 22, 24, 54, 56, 8, 10, 10, 12, 42, 44, 56, 58, 58, 60, 4, 6, 6, 8, 58, 6, 46, 72, 72, 52, 50, 72, 44, 74, 74, 54, 72, 74, 14, 76, 76, 24, 16, 78, 78, 22, 76, 78, 78, 18, 80, 54, 56, 80, 74, 82, 80, 82, 84, 44, 82, 84, 84, 86, 14, 88, 12, 88, 76, 90, 88, 90, 24, 92, 90, 92, 92, 26, 10, 94, 94, 56, 58, 94, 80, 96, 96, 88, 94, 96, 82, 98, 98, 90, 96, 98, 84, 100, 100, 92, 98, 100, 26, 102, 102, 42, 100, 102, 38, 40, 40, 42, 102, 40 ],
					"width": 48,
					"height": 65
				}
			},
			"nose": {
				"nose": { "x": 14.24, "y": 185.5, "width": 41, "height": 45 }
			},
			"ear": {
				"ear": { "x": -2.64, "y": 1, "width": 18, "height": 39 }
			},
			"fat": {
				"fat": { "x": 8.04, "y": 25.97, "width": 314, "height": 139 }
			},
			"l_pupil": {
				"l_pupil": { "x": -0.37, "y": 0.07, "width": 13, "height": 12 }
			},
			"r_eyebrow": {
				"r_eyebrow": { "x": 1.02, "y": -1.53, "width": 46, "height": 17 }
			},
			"hair": {
				"hair": { "x": -7.89, "y": 3.24, "width": 93, "height": 61 }
			},
			"l_eye": {
				"l_eye": { "x": -2.5, "y": 13.1, "width": 68, "height": 67 }
			},
			"head": {
				"head": {
					"type": "mesh",
					"uvs": [ 0.56576, 0.00243, 0.67726, 0.06795, 0.71425, 0.19045, 0.75321, 0.31951, 0.78523, 0.4205, 0.87215, 0.49612, 0.93819, 0.57226, 0.99623, 0.74708, 0.94944, 0.90194, 0.84692, 0.97845, 0.6284, 0.99996, 0.31781, 0.97499, 0.11486, 0.89626, 0.02124, 0.76924, 0.02114, 0.62056, 0.08544, 0.53355, 0.1278, 0.45277, 0.15536, 0.33456, 0.17565, 0.22187, 0.19473, 0.11589, 0.29071, 0.05311, 0.42036, 0.00217 ],
					"triangles": [ 20, 1, 19, 21, 1, 20, 0, 1, 21, 2, 18, 19, 2, 19, 1, 3, 17, 18, 3, 18, 2, 4, 16, 17, 4, 17, 3, 15, 16, 4, 15, 4, 5, 6, 15, 5, 6, 14, 15, 13, 14, 6, 13, 6, 7, 12, 13, 7, 8, 12, 7, 11, 12, 8, 8, 10, 11, 9, 10, 8 ],
					"vertices": [ 1, 7, 242.29, -7.13, 1, 1, 7, 215.5, -37.37, 1, 1, 7, 167.66, -45.59, 1, 1, 7, 117.26, -54.25, 1, 2, 5, 221.81, -59.52, 0.02835, 7, 77.8, -61.46, 0.97165, 2, 5, 192.02, -83.39, 0.19845, 7, 47.43, -84.59, 0.80155, 2, 5, 162.16, -101.37, 0.43559, 7, 17.13, -101.83, 0.56441, 2, 5, 94.16, -116.28, 0.85464, 7, -51.21, -115.04, 0.14536, 2, 5, 34.53, -101.79, 0.98502, 7, -110.47, -99.09, 0.01498, 2, 5, 5.55, -72.25, 0.99979, 7, -138.7, -68.83, 2.1E-4, 1, 5, -1.44, -10.46, 1, 2, 5, 10.11, 76.9, 0.99996, 7, -130.45, 80.15, 4.0E-5, 2, 5, 41.81, 133.46, 0.97025, 7, -97.37, 135.91, 0.02975, 2, 5, 91.52, 158.79, 0.87732, 7, -47.04, 160.01, 0.12268, 2, 5, 149.05, 157.58, 0.6921, 7, 10.44, 157.37, 0.3079, 2, 5, 182.32, 138.72, 0.49827, 7, 43.24, 137.7, 0.50173, 2, 5, 213.32, 126.11, 0.27954, 7, 73.91, 124.31, 0.72046, 2, 5, 258.89, 117.35, 0.0817, 7, 119.25, 114.43, 0.9183, 2, 5, 302.37, 110.69, 0.01459, 7, 162.55, 106.69, 0.98541, 2, 5, 343.25, 104.42, 6.9E-4, 7, 203.27, 99.42, 0.99931, 1, 7, 226.29, 71.25, 1, 1, 7, 244.29, 33.82, 1 ],
					"hull": 22,
					"edges": [ 0, 42, 0, 2, 8, 10, 10, 12, 12, 14, 14, 16, 16, 18, 18, 20, 20, 22, 22, 24, 24, 26, 26, 28, 28, 30, 30, 32, 38, 40, 40, 42, 36, 38, 2, 4, 36, 4, 32, 34, 34, 36, 4, 6, 6, 8, 34, 6, 38, 2, 28, 12, 26, 14, 24, 16, 32, 8, 30, 10 ],
					"width": 282,
					"height": 387
				}
			},
			"nest front": {
				"nest front": { "x": -25.81, "y": 36.11, "width": 231, "height": 140 }
			},
			"body": {
				"body": {
					"type": "mesh",
					"uvs": [ 0.56362, 0, 0.871, 0.08255, 1, 0.1889, 1, 0.19721, 0.97716, 0.28953, 0.95297, 0.38735, 0.92481, 0.50121, 0.95989, 0.53223, 0.96615, 0.59794, 0.9761, 0.70237, 0.98466, 0.7922, 0.95328, 0.88522, 0.91456, 1, 0.89806, 1, 0.68852, 0.97145, 0.40832, 0.93327, 0.23242, 0.90931, 0.16481, 0.84499, 0.08791, 0.77184, 0.00816, 0.69597, 0.00634, 0.56704, 0.00513, 0.4812, 0.00374, 0.38185, 0.00256, 0.29794, 7.2E-4, 0.16737, 0.12496, 0.08329, 0.19494, 0.03592, 0.40956, 0, 0.38139, 0.57911, 0.35162, 0.69824, 0.35423, 0.77789, 0.37124, 0.85552, 0.72168, 0.59007, 0.73324, 0.70077, 0.72797, 0.78637, 0.71651, 0.87314 ],
					"triangles": [ 12, 13, 11, 14, 35, 13, 13, 35, 11, 14, 15, 35, 16, 31, 15, 15, 31, 35, 16, 17, 31, 35, 34, 11, 11, 34, 10, 35, 31, 34, 17, 30, 31, 31, 30, 34, 17, 18, 30, 10, 34, 9, 34, 33, 9, 34, 30, 33, 18, 29, 30, 30, 29, 33, 18, 19, 29, 33, 8, 9, 29, 28, 33, 28, 32, 33, 33, 32, 8, 32, 6, 8, 6, 7, 8, 32, 28, 6, 28, 29, 20, 29, 19, 20, 6, 28, 21, 28, 20, 21, 5, 6, 22, 6, 21, 22, 4, 5, 23, 5, 22, 23, 23, 24, 4, 3, 4, 2, 4, 24, 2, 24, 25, 2, 25, 1, 2, 25, 0, 1, 25, 27, 0, 25, 26, 27 ],
					"vertices": [ 2, 4, 138.4, -20.98, 0.99974, 3, 303.43, -23.54, 2.6E-4, 3, 4, 91.6, -177.29, 0.76003, 3, 253.73, -178.96, 0.22976, 2, 385.34, -177.3, 0.01021, 3, 4, 34.54, -242.01, 0.62075, 3, 195.48, -242.61, 0.33894, 2, 327.51, -241.33, 0.04031, 3, 4, 30.2, -241.9, 0.61909, 3, 191.14, -242.42, 0.34002, 2, 323.17, -241.17, 0.04089, 3, 4, -17.7, -229.08, 0.52155, 3, 143.49, -228.71, 0.39608, 2, 275.43, -227.77, 0.08236, 3, 4, -68.45, -215.48, 0.35128, 3, 92.99, -214.18, 0.45634, 2, 224.84, -213.56, 0.19238, 3, 4, -127.53, -199.66, 0.14045, 3, 34.22, -197.26, 0.39333, 2, 165.96, -197.03, 0.46622, 3, 4, -144.14, -217.24, 0.09108, 3, 17.29, -214.52, 0.33049, 2, 149.14, -214.41, 0.57843, 3, 4, -178.51, -219.63, 0.05453, 3, -17.12, -216.28, 0.25509, 2, 114.74, -216.39, 0.69038, 3, 4, -233.13, -223.43, 0.0163, 3, -71.8, -219.07, 0.1276, 2, 60.08, -219.53, 0.8561, 3, 4, -280.11, -226.71, 0.00398, 3, -118.83, -221.47, 0.05966, 2, 13.07, -222.24, 0.93636, 3, 4, -328.27, -209.49, 2.3E-4, 3, -166.67, -203.37, 0.01892, 2, -34.89, -204.45, 0.98085, 2, 3, -225.69, -181.03, 6.7E-4, 2, -94.06, -182.5, 0.99933, 2, 3, -225.34, -172.58, 5.8E-4, 2, -93.76, -174.05, 0.99942, 4, 4, -370.06, -72.91, 2.0E-5, 3, -205.92, -66.03, 0.03184, 2, -75.03, -67.37, 0.45614, 46, 95.12, -2.66, 0.512, 4, 4, -346.75, 70.04, 5.0E-5, 3, -179.95, 76.46, 0.07405, 2, -50, 75.29, 0.41391, 46, -48.34, 17.27, 0.512, 3, 4, -332.11, 159.78, 1.3E-4, 3, -163.65, 165.92, 0.20602, 2, -34.28, 164.85, 0.79384, 3, 4, -297.73, 193.6, 0.00371, 3, -128.65, 199.09, 0.30748, 2, 0.51, 198.25, 0.68881, 3, 4, -258.62, 232.05, 0.01799, 3, -88.83, 236.81, 0.44896, 2, 40.07, 236.23, 0.53305, 3, 4, -218.06, 271.94, 0.03992, 3, -47.54, 275.94, 0.54423, 2, 81.11, 275.62, 0.41585, 3, 4, -150.76, 271.27, 0.09476, 3, 19.74, 274.03, 0.6245, 2, 148.4, 274.15, 0.28073, 3, 4, -105.95, 270.83, 0.167, 3, 64.53, 272.75, 0.65408, 2, 193.2, 273.17, 0.17892, 3, 4, -54.09, 270.32, 0.28054, 3, 116.38, 271.28, 0.63271, 2, 245.05, 272.03, 0.08675, 3, 4, -10.28, 269.89, 0.38845, 3, 160.16, 270.03, 0.57337, 2, 288.85, 271.07, 0.03818, 3, 4, 57.88, 269.22, 0.51114, 3, 228.31, 268.1, 0.48113, 2, 357, 269.58, 0.00773, 3, 4, 100.25, 204.59, 0.64568, 3, 269.47, 202.69, 0.35402, 2, 398.59, 204.44, 3.0E-4, 2, 4, 124.12, 168.18, 0.73975, 3, 292.66, 165.84, 0.26025, 2, 4, 140.27, 57.88, 0.96835, 3, 306.76, 55.27, 0.03165, 3, 4, -161.6, 79.45, 0.07904, 3, 5.34, 82.44, 0.48015, 2, 135.25, 82.47, 0.44081, 3, 4, -223.41, 96.16, 0.03154, 3, -56.15, 100.29, 0.39639, 2, 73.65, 99.92, 0.57207, 4, 4, -265, 95.81, 0.01272, 3, -97.74, 100.71, 0.30668, 2, 32.05, 100.07, 0.6006, 46, -76.04, 98.38, 0.08, 4, 4, -305.72, 88.06, 0.0015, 3, -138.6, 93.72, 0.12432, 2, -8.76, 92.82, 0.41018, 46, -67.33, 57.86, 0.464, 3, 4, -171.44, -94.59, 0.06478, 3, -7.73, -91.39, 0.34918, 2, 123.32, -91.44, 0.58604, 3, 4, -229.35, -99.14, 0.02223, 3, -65.71, -94.87, 0.23214, 2, 65.36, -95.29, 0.74564, 4, 4, -273.96, -95.39, 0.00735, 3, -110.25, -90.29, 0.15741, 2, 20.8, -91.01, 0.75524, 46, 115.32, 93.96, 0.08, 4, 4, -319.1, -88.45, 9.3E-4, 3, -155.25, -82.51, 0.07686, 2, -24.26, -83.52, 0.65021, 46, 109.45, 48.66, 0.272 ],
					"hull": 28,
					"edges": [ 0, 54, 0, 2, 2, 4, 4, 6, 12, 14, 24, 26, 52, 54, 46, 48, 6, 8, 46, 8, 44, 46, 8, 10, 10, 12, 44, 10, 42, 44, 42, 12, 38, 40, 40, 42, 14, 16, 36, 38, 32, 34, 34, 36, 20, 22, 22, 24, 16, 18, 18, 20, 48, 4, 48, 50, 50, 52, 50, 2, 56, 40, 58, 38, 56, 58, 60, 36, 58, 60, 62, 34, 60, 62, 30, 32, 62, 30, 16, 64, 64, 56, 18, 66, 66, 58, 64, 66, 20, 68, 68, 60, 66, 68, 22, 70, 70, 62, 68, 70, 26, 28, 28, 30, 70, 28 ],
					"width": 512,
					"height": 522
				}
			},
			"r_eye": {
				"r_eye": { "x": -0.4, "y": 15.07, "width": 71, "height": 68 }
			},
			"legs": {
				"legs": {
					"type": "mesh",
					"uvs": [ 0.16227, 0.35315, 0.20281, 0.50496, 0.29072, 0.55864, 0.41526, 0.59294, 0.50656, 0.58932, 0.56749, 0.56159, 0.62988, 0.5332, 0.69068, 0.41057, 0.6901, 0.40646, 0.71258, 0.52163, 0.72043, 0.5618, 0.72623, 0.59154, 0.73048, 0.61326, 0.72605, 0.64527, 0.72211, 0.67367, 0.7163, 0.71565, 0.71227, 0.74484, 0.70852, 0.77189, 0.70387, 0.80552, 0.6989, 0.84142, 0.69475, 0.8714, 0.69024, 0.90395, 0.68534, 0.9394, 0.67883, 0.98639, 0.61582, 1, 0.55626, 1, 0.56448, 0.94107, 0.61089, 0.90804, 0.6053, 0.87569, 0.60011, 0.84559, 0.58731, 0.81397, 0.57951, 0.7915, 0.55744, 0.76244, 0.53654, 0.73493, 0.49472, 0.68736, 0.43382, 0.69672, 0.43888, 0.71254, 0.44806, 0.74121, 0.45605, 0.76759, 0.46186, 0.78678, 0.45894, 0.8232, 0.45736, 0.84304, 0.42534, 0.90061, 0.40891, 0.93016, 0.43194, 0.95267, 0.42576, 0.99999, 0.34833, 0.99889, 0.29521, 0.99814, 0.29919, 0.919, 0.33387, 0.90442, 0.34211, 0.88299, 0.35141, 0.8588, 0.34444, 0.8414, 0.33587, 0.82001, 0.32658, 0.80386, 0.3196, 0.79172, 0.24449, 0.79929, 0.16588, 0.7194, 0.147, 0.70021, 0.11382, 0.66649, 0.09001, 0.6423, 0.07361, 0.62563, 0, 0.55082, 0, 0.47647, 0.03737, 0.30075, 0.41305, 0.61564, 0.42262, 0.64147, 0.50984, 0.6088, 0.50894, 0.63238, 0.42819, 0.66758, 0.50664, 0.65702, 0.27435, 0.62708, 0.2941, 0.65188, 0.31693, 0.68049, 0.34008, 0.70465, 0.37938, 0.76883, 0.3904, 0.80531, 0.39258, 0.84976, 0.36782, 0.91308, 0.35878, 0.94056, 0.59318, 0.57818, 0.60675, 0.60107, 0.62164, 0.62265, 0.62652, 0.6506, 0.63081, 0.67917, 0.63554, 0.72431, 0.63923, 0.78241, 0.64043, 0.80945, 0.64016, 0.84188, 0.63861, 0.90549, 0.63183, 0.94014, 0.39159, 0.8296, 0.38501, 0.78749, 0.63741, 0.75371, 0.63942, 0.87217, 0.36123, 0.7392, 0.3792, 0.88396 ],
					"triangles": [ 33, 34, 84, 87, 30, 86, 30, 31, 86, 87, 86, 18, 18, 86, 17, 86, 31, 93, 31, 32, 93, 86, 93, 17, 17, 93, 16, 93, 32, 85, 32, 33, 85, 93, 85, 16, 16, 85, 15, 33, 84, 85, 85, 84, 15, 15, 84, 14, 84, 70, 83, 84, 83, 14, 14, 83, 13, 83, 68, 82, 83, 70, 68, 70, 66, 68, 83, 82, 13, 13, 82, 12, 68, 81, 82, 68, 67, 81, 82, 11, 12, 82, 81, 11, 67, 80, 81, 81, 10, 11, 81, 80, 10, 10, 6, 9, 10, 80, 6, 80, 5, 6, 9, 6, 7, 9, 7, 8, 68, 66, 67, 4, 5, 80, 84, 34, 70, 23, 90, 22, 26, 27, 90, 90, 89, 22, 90, 27, 89, 22, 89, 21, 27, 28, 89, 89, 94, 21, 89, 28, 94, 21, 94, 20, 28, 29, 94, 94, 88, 20, 94, 29, 88, 20, 88, 19, 88, 29, 87, 88, 87, 19, 87, 29, 30, 19, 87, 18, 24, 90, 23, 25, 26, 24, 24, 26, 90, 44, 45, 79, 45, 46, 79, 79, 43, 44, 46, 47, 79, 53, 76, 91, 47, 48, 79, 48, 49, 79, 79, 78, 43, 79, 49, 78, 42, 43, 96, 49, 50, 78, 43, 78, 96, 78, 50, 96, 96, 77, 42, 42, 77, 41, 50, 51, 96, 96, 51, 77, 51, 52, 77, 52, 91, 77, 77, 91, 41, 41, 91, 40, 52, 53, 91, 91, 76, 40, 95, 74, 35, 76, 53, 92, 53, 54, 92, 76, 92, 39, 92, 54, 75, 95, 55, 56, 54, 55, 75, 55, 95, 75, 95, 56, 74, 74, 56, 57, 92, 38, 39, 92, 75, 38, 75, 37, 38, 37, 75, 36, 75, 95, 36, 95, 35, 36, 57, 73, 74, 57, 58, 73, 58, 72, 73, 58, 59, 72, 73, 72, 66, 59, 71, 72, 59, 60, 71, 72, 65, 66, 72, 71, 65, 71, 60, 2, 2, 60, 61, 61, 1, 2, 61, 62, 1, 62, 63, 1, 63, 0, 1, 63, 64, 0, 40, 76, 39, 74, 73, 69, 74, 69, 35, 35, 69, 34, 34, 69, 70, 71, 2, 65, 67, 65, 3, 67, 3, 4, 65, 2, 3, 67, 4, 80, 69, 66, 70, 67, 66, 65, 73, 66, 69 ],
					"vertices": [ 2, 22, -98.42, 59.93, 1, 26, -95.13, -288.1, 0, 2, 22, -3.51, 17.36, 1, 26, 5.6, -262.17, 0, 3, 21, 39.43, -75.07, 0.928, 22, 58.1, 38.1, 0.07184, 26, 40.83, -207.54, 1.6E-4, 3, 21, 64.45, 1.2, 0.85941, 22, 123.54, 84.6, 0.06852, 26, 62.97, -130.37, 0.07207, 2, 21, 63.67, 57.68, 0.91573, 26, 60.07, -73.97, 0.08427, 2, 21, 46.32, 95.84, 0.25686, 26, 41.31, -36.48, 0.74314, 1, 26, 22.09, 1.91, 1, 2, 21, -51.87, 174.84, 8.3E-4, 26, -59.78, 38.78, 0.99917, 2, 21, -54.62, 174.56, 8.3E-4, 26, -62.51, 38.39, 0.99917, 2, 21, 22.34, 186.24, 3.7E-4, 26, 13.95, 52.95, 0.99963, 2, 21, 49.19, 190.32, 1.2E-4, 26, 40.63, 58.03, 0.99988, 2, 21, 69.06, 193.33, 6.0E-5, 26, 60.37, 61.79, 0.99994, 2, 21, 83.57, 195.54, 1.0E-5, 26, 74.79, 64.54, 0.99999, 2, 21, 104.77, 192.18, 0, 26, 96.1, 61.98, 1, 1, 26, 115.01, 59.72, 1, 2, 27, -54.8, 66.54, 0.08, 26, 142.95, 56.37, 0.92, 2, 27, -36.04, 60.97, 0.15977, 26, 162.38, 54.04, 0.84023, 2, 27, -18.67, 55.81, 0.26018, 26, 180.39, 51.89, 0.73982, 2, 27, 2.95, 49.41, 0.42662, 26, 202.78, 49.2, 0.57338, 2, 27, 26.04, 42.57, 0.81361, 26, 226.68, 46.34, 0.18639, 2, 27, 45.31, 36.87, 0.90296, 26, 246.62, 43.96, 0.09704, 1, 27, 66.23, 30.67, 1, 2, 28, -19.1, 13.35, 0.15032, 27, 89.02, 23.92, 0.84968, 2, 28, 4.85, 33.82, 0.84551, 27, 119.24, 14.97, 0.15449, 2, 29, -2.68, 16.05, 0.48422, 28, 39.79, 14.39, 0.51578, 1, 29, 34, 12.93, 1, 3, 29, 25.61, -25.69, 0.57408, 28, 37.01, -35.96, 0.15944, 27, 78.22, -49.99, 0.26648, 3, 29, -4.82, -45.15, 0.21504, 28, 1.01, -33, 0.12046, 27, 61.1, -18.18, 0.6645, 4, 29, -3.2, -66.87, 0.10879, 28, -10.86, -51.26, 0.05889, 27, 39.32, -18.16, 0.79277, 26, 249.97, -11.29, 0.03955, 4, 29, -1.71, -87.09, 0.00991, 28, -21.93, -68.25, 0.00159, 27, 19.05, -18.14, 0.91215, 26, 229.98, -14.69, 0.07635, 4, 21, 214.44, 103.25, 0.00118, 29, 4.4, -108.71, 5.3E-4, 27, -2.97, -22.6, 0.56289, 26, 209.02, -22.78, 0.4354, 3, 21, 199.36, 98.86, 0.00671, 27, -18.49, -24.98, 0.17464, 26, 194.13, -27.73, 0.81865, 4, 21, 179.65, 85.77, 0.10749, 22, 266.44, 84.19, 0.03199, 27, -39.75, -35.35, 0.14386, 26, 174.92, -41.53, 0.71666, 4, 21, 160.99, 73.39, 0.29259, 22, 244.08, 85.32, 0.08981, 27, -59.87, -45.17, 0.16548, 26, 156.74, -54.6, 0.45212, 3, 21, 128.62, 48.47, 0.66624, 22, 203.24, 84.5, 0.21532, 27, -95.23, -65.63, 0.11843, 4, 21, 133.76, 10.68, 0.38576, 22, 184.93, 51.05, 0.3603, 23, -65.49, -19.65, 0.20415, 26, 131.88, -118.3, 0.04979, 4, 21, 144.36, 13.5, 0.21887, 22, 195.13, 47.02, 0.43025, 23, -57.52, -12.1, 0.31021, 26, 142.38, -115.07, 0.04067, 4, 21, 163.59, 18.62, 0.0907, 22, 213.64, 39.72, 0.58838, 23, -43.09, 1.59, 0.3139, 26, 161.39, -109.25, 0.00702, 4, 21, 181.27, 23.05, 0.06917, 22, 230.49, 32.78, 0.53772, 23, -29.68, 13.93, 0.38849, 26, 178.9, -104.14, 0.00461, 4, 21, 194.13, 26.27, 0.02601, 22, 242.75, 27.74, 0.61459, 23, -19.92, 22.9, 0.35893, 26, 191.62, -100.46, 4.8E-4, 5, 21, 218.28, 23.78, 0.01157, 22, 260.7, 11.38, 0.28441, 23, 2.49, 32.26, 0.69543, 25, 33.58, 115.18, 0.00838, 26, 215.86, -102.03, 2.1E-4, 3, 22, 270.48, 2.47, 0.208, 23, 14.7, 37.35, 0.7824, 25, 35.95, 102.17, 0.0096, 4, 22, 288.4, -36.72, 0.056, 23, 57.79, 37.03, 0.66903, 24, 10.29, 63.62, 0.00238, 25, 26.46, 60.13, 0.27259, 3, 23, 79.91, 36.87, 0.56768, 24, 19.8, 43.65, 0.0038, 25, 21.59, 38.55, 0.42851, 3, 23, 86.82, 56.33, 0.28985, 24, 40.32, 45.94, 0.00339, 25, 39.13, 27.66, 0.70676, 1, 25, 43.37, -3.76, 1, 3, 23, 137.61, 24.17, 0.0141, 24, 33.57, -13.81, 0.57862, 25, -3.12, -15.12, 0.40728, 3, 23, 152.02, -5.34, 0.02378, 24, 13.32, -39.65, 0.97557, 25, -35.01, -22.91, 6.5E-4, 2, 23, 103.98, -26.96, 0.79265, 24, -27.11, -5.88, 0.20735, 1, 23, 85.63, -12.23, 1, 2, 22, 247.44, -69.98, 0.0156, 23, 70.62, -14.14, 0.9844, 2, 22, 238.33, -55.53, 0.03321, 23, 53.67, -16.29, 0.96679, 2, 22, 226.57, -51.78, 0.28895, 23, 45.3, -25.37, 0.71105, 2, 22, 212.11, -47.17, 0.40286, 23, 35.02, -36.53, 0.59714, 3, 21, 203.07, -57.62, 0.048, 22, 200.11, -45.07, 0.57229, 23, 28.04, -46.51, 0.37971, 4, 21, 194.87, -61.7, 0.056, 22, 191.09, -43.48, 0.72954, 23, 22.79, -54.01, 0.09675, 26, 195.66, -188.35, 0.11771, 2, 21, 198.57, -108.25, 0.112, 22, 166.42, -83.12, 0.888, 1, 22, 94.64, -88.58, 1, 1, 22, 77.4, -89.89, 1, 1, 22, 47.1, -92.19, 1, 1, 22, 25.36, -93.84, 1, 1, 22, 10.38, -94.98, 1, 1, 22, -56.83, -100.1, 1, 2, 22, -95.75, -69.59, 1, 26, -12.26, -387.67, 0, 2, 22, -173.46, 20.67, 1, 26, -129.3, -365.59, 0, 4, 21, 79.5, -0.6, 0.31203, 22, 134.57, 74.2, 0.29793, 23, -107.75, -55.5, 0.06054, 26, 78.09, -131.61, 0.3295, 4, 21, 96.84, 4.81, 0.352, 22, 151.74, 68.26, 0.27464, 23, -95.11, -42.46, 0.07151, 26, 95.22, -125.54, 0.30185, 3, 21, 76.68, 59.32, 0.432, 22, 167.9, 124.08, 0.1932, 26, 73.02, -71.83, 0.3748, 3, 21, 92.34, 58.31, 0.26401, 22, 179.9, 113.97, 0.2703, 26, 88.71, -72.25, 0.4657, 4, 21, 114.29, 7.76, 0.59743, 22, 167.53, 60.26, 0.23699, 23, -81.19, -31.53, 0.08793, 26, 112.54, -121.95, 0.07765, 4, 21, 108.67, 56.42, 0.24855, 22, 191.91, 102.74, 0.33773, 27, -113.96, -55.15, 0.00772, 26, 105.1, -73.53, 0.406, 3, 21, 84.63, -86.5, 2.0E-5, 22, 87.68, 2.05, 0.70031, 26, 86.45, -217.25, 0.29967, 3, 21, 101.47, -74.77, 0, 22, 108.19, 1.48, 0.699, 26, 102.84, -204.9, 0.30099, 3, 21, 120.89, -61.22, 0.6122, 22, 131.87, 0.85, 0.29104, 26, 121.73, -190.62, 0.09677, 3, 21, 137.36, -47.38, 0.52573, 22, 153.34, 2.2, 0.46277, 26, 137.67, -176.17, 0.0115, 4, 21, 180.73, -24.33, 0.07971, 22, 201.91, -5.02, 0.81687, 23, -7.5, -27.95, 0.09725, 26, 180.14, -151.52, 0.00617, 4, 21, 205.17, -18.22, 0.01447, 22, 225.2, -14.62, 0.57281, 23, 11.05, -10.9, 0.41245, 26, 204.33, -144.49, 2.6E-4, 3, 22, 249.3, -31.8, 0.02633, 23, 36.8, 3.68, 0.96899, 25, -1.66, 87.74, 0.00469, 3, 23, 81.28, 9.08, 0.82162, 24, -4.6, 30.29, 0.00157, 25, -5.85, 43.14, 0.17681, 3, 23, 100.1, 12.37, 0.56489, 24, 6.58, 14.79, 0.11495, 25, -6.65, 24.05, 0.32015, 2, 21, 57.8, 111.39, 0.30216, 26, 52.2, -20.51, 0.69784, 3, 21, 73.27, 119.34, 5.0E-5, 22, 200.8, 174.39, 0.1878, 26, 67.35, -11.99, 0.81216, 3, 21, 87.88, 128.12, 1.0E-5, 22, 217.77, 172.77, 0.1765, 26, 81.63, -2.67, 0.8235, 4, 21, 106.54, 130.59, 0.06561, 22, 234.26, 163.68, 0.1198, 27, -106.36, 18.67, 0.01125, 26, 100.18, 0.51, 0.80334, 4, 21, 125.61, 132.7, 0.14878, 22, 250.85, 154.05, 0.04637, 27, -87.18, 18.26, 0.02551, 26, 119.15, 3.33, 0.77934, 4, 21, 155.7, 134.75, 0.09115, 22, 276.27, 137.82, 0.02798, 27, -57.08, 16.35, 0.08266, 26, 149.15, 6.51, 0.79821, 3, 21, 194.39, 135.91, 0.00378, 27, -18.57, 12.43, 0.15609, 26, 187.76, 9.13, 0.84013, 4, 21, 212.38, 136.13, 6.2E-4, 29, -28.55, -108.93, 2.8E-4, 27, -0.71, 10.29, 0.49776, 26, 205.73, 10.02, 0.50135, 4, 29, -26.56, -87.45, 0.00482, 28, -41.92, -53.48, 7.7E-4, 27, 20.55, 6.69, 0.86159, 26, 227.3, 10.05, 0.13282, 3, 29, -22.03, -45.38, 0.0917, 28, -12.82, -22.75, 0.05136, 27, 62.16, -1, 0.85694, 3, 29, -15.91, -22.78, 0.25419, 28, 5.74, -8.49, 0.15436, 27, 84.24, -8.81, 0.59145, 5, 21, 221.34, -17.96, 0.00656, 22, 238.37, -24.01, 0.27416, 23, 25.12, -2.94, 0.71659, 25, -5.63, 100.56, 0.00256, 26, 220.48, -143.61, 1.2E-4, 4, 21, 193.23, -21.21, 0.04634, 22, 213.82, -9.93, 0.69204, 23, 1.99, -19.23, 0.25847, 26, 192.51, -147.92, 0.00315, 4, 21, 175.27, 135.33, 0.04695, 22, 292.37, 126.67, 0.01382, 27, -37.6, 14.36, 0.11981, 26, 168.68, 7.83, 0.81942, 4, 29, -24.4, -67.42, 0.04619, 28, -28.06, -38.85, 0.02486, 27, 40.37, 3.03, 0.85937, 26, 247.44, 9.78, 0.06957, 4, 21, 160.7, -34.98, 0.26055, 22, 179.48, -1.69, 0.60438, 23, -20, -46.87, 0.05537, 26, 160.53, -162.9, 0.0797, 4, 22, 262.1, -52.33, 0.01211, 23, 60.82, 6.6, 0.8894, 24, -15.77, 47.6, 8.5E-4, 25, -3.92, 63.65, 0.09764 ],
					"hull": 65,
					"edges": [ 0, 128, 0, 2, 2, 4, 4, 6, 6, 8, 12, 14, 14, 16, 46, 48, 48, 50, 94, 96, 110, 112, 124, 126, 126, 128, 60, 62, 58, 60, 36, 38, 34, 36, 50, 52, 52, 54, 42, 44, 44, 46, 96, 98, 86, 88, 88, 90, 112, 114, 122, 124, 122, 4, 124, 2, 16, 18, 18, 20, 12, 18, 118, 120, 120, 122, 20, 22, 22, 24, 6, 130, 130, 132, 134, 130, 8, 134, 136, 132, 134, 136, 68, 70, 114, 116, 116, 118, 70, 138, 138, 132, 68, 140, 140, 136, 138, 140, 24, 26, 26, 28, 66, 68, 28, 30, 120, 142, 142, 130, 4, 142, 118, 144, 144, 132, 142, 144, 116, 146, 146, 138, 144, 146, 70, 148, 148, 114, 146, 148, 74, 150, 150, 110, 78, 152, 152, 106, 82, 154, 154, 102, 86, 156, 156, 98, 88, 158, 158, 96, 156, 158, 90, 92, 92, 94, 158, 92, 8, 10, 10, 12, 8, 160, 160, 20, 10, 160, 22, 162, 162, 134, 160, 162, 24, 164, 164, 136, 162, 164, 26, 166, 166, 140, 164, 166, 28, 168, 168, 68, 166, 168, 30, 170, 170, 66, 168, 170, 34, 172, 172, 62, 36, 174, 174, 60, 172, 174, 38, 176, 176, 58, 174, 176, 42, 178, 178, 54, 44, 180, 180, 52, 178, 180, 180, 48, 102, 104, 104, 106, 152, 182, 182, 154, 104, 182, 78, 80, 80, 82, 182, 80, 106, 108, 108, 110, 150, 184, 184, 152, 108, 184, 74, 76, 76, 78, 184, 76, 62, 64, 64, 66, 170, 186, 186, 172, 64, 186, 30, 32, 32, 34, 186, 32, 54, 56, 56, 58, 176, 188, 188, 178, 56, 188, 38, 40, 40, 42, 188, 40, 148, 190, 190, 150, 112, 190, 70, 72, 72, 74, 190, 72, 98, 100, 100, 102, 154, 192, 192, 156, 100, 192, 82, 84, 84, 86, 192, 84 ],
					"width": 618,
					"height": 665
				}
			},
			"cheeks": {
				"cheeks": { "x": 65.47, "y": -0.26, "width": 163, "height": 42 }
			},
			"casc": {
				"casc": { "x": -8.64, "y": -12.7, "width": 172, "height": 146 }
			},
			"nest back": {
				"nest back": { "x": -37.76, "y": 70.8, "width": 188, "height": 133 }
			},
			"l_eyebrow": {
				"l_eyebrow": { "x": -4.38, "y": -0.27, "width": 39, "height": 17 }
			},
			"yellow bird": {
				"yellow bird": {
					"type": "mesh",
					"uvs": [ 0.46662, 0.15432, 0.6105, 0, 0.64305, 0.02107, 0.64362, 0.2025, 0.64377, 0.25062, 0.69093, 0.23578, 0.85613, 0.18377, 0.76686, 0.3096, 0.72136, 0.37372, 0.71063, 0.38884, 0.69671, 0.40846, 0.67937, 0.4329, 0.68316, 0.48645, 0.63491, 0.53275, 0.60858, 0.55801, 0.65346, 0.55709, 0.72978, 0.55553, 0.77933, 0.55451, 0.92414, 0.60415, 0.97448, 0.64743, 0.80326, 0.64762, 0.751, 0.66473, 0.68494, 0.68636, 0.62356, 0.70645, 0.62545, 0.80161, 0.62757, 0.90915, 0.22365, 0.99873, 0.11589, 0.97584, 0.16851, 0.82827, 0.19288, 0.78507, 0.13213, 0.74642, 0.0873, 0.71692, 0.00984, 0.66595, 0.01836, 0.64433, 0.02667, 0.62326, 0.15311, 0.62332, 0.23249, 0.62335, 0.29096, 0.63277, 0.21089, 0.54905, 0.11457, 0.44835, 0.13923, 0.32713, 0.23075, 0.23534, 0.37125, 0.20433, 0.40022, 0.19794, 0.43261, 0.19079, 0.55895, 0.32206, 0.60002, 0.28747, 0.12169, 0.66801, 0.18208, 0.68517, 0.24667, 0.70155, 0.61945, 0.66567, 0.67424, 0.6424, 0.74285, 0.62275, 0.79017, 0.61271 ],
					"triangles": [ 7, 5, 6, 7, 4, 5, 4, 8, 46, 7, 8, 4, 9, 45, 46, 8, 9, 46, 10, 45, 9, 11, 45, 10, 0, 1, 2, 3, 0, 2, 44, 0, 3, 4, 44, 3, 46, 44, 4, 43, 44, 46, 45, 43, 46, 42, 43, 45, 41, 42, 45, 45, 40, 41, 11, 40, 45, 39, 40, 11, 39, 11, 12, 12, 38, 39, 13, 38, 12, 14, 38, 13, 14, 37, 38, 53, 17, 18, 53, 52, 16, 53, 16, 17, 52, 51, 15, 52, 15, 16, 53, 18, 19, 20, 53, 19, 52, 53, 20, 21, 52, 20, 51, 52, 21, 51, 50, 14, 51, 14, 15, 37, 14, 50, 22, 51, 21, 50, 51, 22, 23, 50, 22, 49, 50, 23, 29, 23, 24, 28, 24, 25, 47, 34, 35, 33, 34, 47, 32, 33, 47, 48, 35, 36, 47, 35, 48, 49, 36, 37, 48, 36, 49, 49, 37, 50, 31, 32, 47, 48, 31, 47, 30, 31, 48, 49, 30, 48, 29, 30, 49, 29, 49, 23, 28, 29, 24, 26, 27, 28, 25, 26, 28 ],
					"vertices": [ 2, 49, 34.98, 8.23, 0.02379, 50, 14.8, 5.34, 0.97621, 1, 50, 28.77, -1.13, 1, 1, 50, 27.2, -3.15, 1, 2, 50, 11.89, -4.98, 0.91615, 51, 10.71, 7.72, 0.08385, 2, 50, 7.83, -5.47, 0.42076, 51, 8.56, 4.24, 0.57924, 2, 50, 9.39, -7.95, 0.06744, 51, 11.47, 3.92, 0.93256, 1, 51, 21.66, 2.79, 1, 2, 48, 35.52, -21.01, 4.0E-5, 51, 11.77, -3.66, 0.99996, 4, 48, 30.28, -18.04, 0.00687, 52, 24.69, 19.02, 0.00127, 49, 21.56, -11.04, 0.0585, 51, 6.73, -6.94, 0.93336, 4, 48, 29.05, -17.34, 0.0122, 52, 23.62, 18.08, 0.00327, 49, 20.16, -10.86, 0.11333, 51, 5.54, -7.72, 0.8712, 4, 48, 27.45, -16.44, 0.02349, 52, 22.24, 16.87, 0.00864, 49, 18.33, -10.63, 0.21569, 51, 4, -8.72, 0.75217, 4, 48, 25.45, -15.3, 0.05013, 52, 20.51, 15.36, 0.02419, 49, 16.06, -10.34, 0.37677, 51, 2.08, -9.97, 0.5489, 4, 48, 20.9, -15.16, 0.1236, 52, 18.88, 11.1, 0.08005, 49, 11.78, -11.93, 0.51084, 51, -0.14, -13.95, 0.2855, 4, 48, 17.19, -12.16, 0.22696, 52, 14.82, 8.59, 0.22078, 49, 7.21, -10.55, 0.43447, 51, -4.51, -15.87, 0.11779, 4, 48, 15.16, -10.52, 0.26784, 52, 12.61, 7.21, 0.49576, 49, 4.72, -9.8, 0.20031, 51, -6.9, -16.92, 0.03609, 4, 48, 15.04, -13.03, 0.12267, 52, 14.94, 6.27, 0.81041, 49, 5.56, -12.17, 0.05694, 51, -4.72, -18.17, 0.00998, 4, 48, 14.84, -17.3, 0.01561, 52, 18.91, 4.68, 0.97964, 49, 6.99, -16.2, 0.00405, 51, -1.02, -20.32, 7.1E-4, 2, 48, 14.71, -20.07, 0.00136, 52, 21.48, 3.64, 0.99864, 1, 52, 27.21, -3.48, 1, 1, 52, 28.31, -7.99, 1, 1, 52, 19.53, -4.14, 1, 1, 52, 16.26, -4.3, 1, 2, 48, 3.95, -13.93, 2.2E-4, 52, 12.13, -4.49, 0.99978, 2, 48, 2.52, -10.37, 0.06394, 52, 8.3, -4.68, 0.93606, 3, 59, -18.38, -2.77, 0.00761, 48, -5.56, -9.84, 0.64181, 52, 5.14, -12.12, 0.35059, 3, 59, -22.69, 5.29, 0.07079, 48, -14.68, -9.24, 0.82875, 52, 1.58, -20.54, 0.10046, 2, 59, -6.1, 22.45, 0.64912, 48, -20.49, 13.91, 0.35088, 2, 59, 0.15, 23.5, 0.68448, 48, -18.08, 19.77, 0.31552, 2, 59, 3.3, 11.01, 0.80713, 48, -5.81, 15.85, 0.19287, 2, 59, 3.78, 7.12, 0.92976, 48, -2.25, 14.2, 0.07024, 1, 59, 8.31, 5.76, 1, 1, 59, 11.69, 4.69, 1, 1, 59, 17.54, 2.84, 1, 1, 59, 17.96, 0.99, 1, 1, 59, 18.37, -0.82, 1, 3, 59, 12.08, -4.07, 0.98653, 48, 11.63, 15.34, 0.00141, 49, -8.34, 12.8, 0.01206, 4, 59, 8.13, -6.11, 0.84802, 48, 11.27, 10.91, 0.04876, 49, -6.99, 8.56, 0.10322, 50, -26.33, 13.7, 0, 4, 59, 4.85, -6.9, 0.45958, 48, 10.22, 7.71, 0.18441, 49, -6.75, 5.2, 0.35553, 50, -26.74, 10.36, 4.8E-4, 3, 59, 12.11, -11.16, 0.02527, 49, -1.34, 11.64, 0.93962, 50, -20.2, 15.64, 0.03511, 2, 49, 5.17, 19.39, 0.85231, 50, -12.33, 22, 0.14769, 2, 49, 15.4, 21.21, 0.69221, 50, -1.93, 21.83, 0.30779, 2, 49, 24.39, 18.71, 0.51664, 50, 6.42, 17.65, 0.48336, 2, 49, 29.3, 12.02, 0.29008, 50, 9.95, 10.14, 0.70992, 2, 49, 30.31, 10.64, 0.21962, 50, 10.68, 8.6, 0.78038, 2, 49, 31.44, 9.1, 0.12734, 50, 11.5, 6.87, 0.87266, 2, 50, 1.24, -1.46, 0.52051, 51, 1.32, 1.59, 0.47949, 2, 50, 4.43, -3.4, 0.43589, 51, 4.83, 2.87, 0.56411, 1, 59, 11.89, 0.11, 1, 3, 59, 8.22, -0.15, 0.99901, 48, 6.26, 14.14, 3.0E-4, 49, -12.85, 9.65, 6.9E-4, 3, 59, 4.37, -0.57, 0.98271, 48, 4.59, 10.64, 0.00937, 49, -13.08, 5.78, 0.00792, 1, 52, 9.48, -1.41, 1, 1, 52, 13.09, -0.83, 1, 1, 52, 17.28, -0.85, 1, 1, 52, 20.05, -1.13, 1 ],
					"hull": 45,
					"edges": [ 2, 4, 36, 38, 38, 40, 50, 52, 52, 54, 54, 56, 56, 58, 78, 80, 80, 82, 74, 28, 22, 24, 78, 24, 80, 22, 8, 16, 88, 8, 82, 84, 20, 22, 8, 10, 10, 12, 12, 14, 14, 16, 10, 14, 2, 0, 0, 88, 4, 6, 6, 8, 0, 6, 20, 90, 90, 84, 8, 92, 92, 90, 16, 18, 18, 20, 92, 18, 84, 86, 86, 88, 92, 86, 34, 36, 28, 30, 44, 46, 30, 32, 32, 34, 40, 42, 42, 44, 72, 74, 58, 60, 68, 70, 70, 72, 60, 62, 62, 64, 58, 46, 46, 48, 48, 50, 56, 48, 74, 76, 76, 78, 24, 26, 26, 28, 76, 26, 64, 66, 66, 68, 62, 94, 94, 70, 66, 94, 60, 96, 96, 72, 94, 96, 58, 98, 98, 74, 96, 98, 28, 100, 100, 46, 98, 100, 30, 102, 102, 44, 100, 102, 32, 104, 104, 42, 102, 104, 104, 106, 106, 38, 34, 106, 40, 106 ],
					"width": 56,
					"height": 85
				}
			}
		}
	}
],
"animations": {
	"active": {
		"bones": {
			"hip": {
				"rotate": [
					{ "curve": "stepped" },
					{ "time": 2.3333 }
				],
				"translate": [
					{ "y": -27.81, "curve": 0.261, "c3": 0.618, "c4": 0.44 },
					{
						"time": 0.3667,
						"x": 4.56,
						"y": -54.1,
						"curve": 0.328,
						"c2": 0.32,
						"c3": 0.672,
						"c4": 0.68
					},
					{
						"time": 0.6333,
						"x": 38.91,
						"y": -19.94,
						"curve": 0.344,
						"c2": 0.37,
						"c3": 0.681,
						"c4": 0.71
					},
					{
						"time": 0.7667,
						"x": 38.03,
						"y": -7.53,
						"curve": 0.349,
						"c2": 0.4,
						"c3": 0.684,
						"c4": 0.74
					},
					{ "time": 0.8667, "x": 56.3, "y": -8.22, "curve": 0.366, "c2": 0.63, "c3": 0.703 },
					{ "time": 0.9333, "x": 66.94, "y": -10.61, "curve": 0.312, "c3": 0.646, "c4": 0.35 },
					{
						"time": 1,
						"x": 47.55,
						"y": -10.2,
						"curve": 0.317,
						"c2": 0.23,
						"c3": 0.651,
						"c4": 0.57
					},
					{
						"time": 1.2333,
						"x": 38.72,
						"y": -19.03,
						"curve": 0.321,
						"c2": 0.28,
						"c3": 0.655,
						"c4": 0.62
					},
					{
						"time": 1.4,
						"x": 47.55,
						"y": -10.2,
						"curve": 0.304,
						"c2": 0.18,
						"c3": 0.641,
						"c4": 0.54
					},
					{
						"time": 1.5667,
						"x": 59.93,
						"y": -9.21,
						"curve": 0.324,
						"c2": 0.3,
						"c3": 0.662,
						"c4": 0.65
					},
					{ "time": 1.7333, "x": 56.79, "y": -1.67, "curve": 0.375, "c2": 0.5, "c3": 0.75 },
					{ "time": 1.9333, "x": -1.65, "y": -7.21, "curve": 0.25, "c3": 0.75 },
					{ "time": 2.3333, "y": -27.81 }
				]
			},
			"head": {
				"rotate": [
					{ "curve": "stepped" },
					{ "time": 2.3333 }
				],
				"translate": [
					{ "curve": 0.25, "c3": 0.75 },
					{ "time": 0.8333, "x": 6.72, "y": 0.97, "curve": 0.25, "c3": 0.75 },
					{ "time": 1.6333, "x": -3.47, "y": -2.73, "curve": 0.25, "c3": 0.75 },
					{ "time": 2.3333 }
				]
			},
			"head1": {
				"rotate": [
					{ "curve": "stepped" },
					{ "time": 0.6667 },
					{ "time": 0.8, "angle": 1.11 },
					{ "time": 0.9333, "angle": -0.92 },
					{ "time": 1.0333 },
					{ "time": 1.4667, "angle": 1.65 },
					{ "time": 1.6667, "angle": -1.31 },
					{ "time": 1.8333, "angle": 2.61 },
					{ "time": 2.3333 }
				],
				"translate": [
					{ "curve": 0.243, "c3": 0.658, "c4": 0.64 },
					{ "time": 0.5, "x": 27.77, "y": 1.69, "curve": 0.381, "c2": 0.59, "c3": 0.729 },
					{ "time": 0.7, "x": 16.49, "y": 0.71, "curve": 0.25, "c3": 0.625, "c4": 0.5 },
					{
						"time": 0.8333,
						"x": 14.91,
						"y": -18.41,
						"curve": 0.339,
						"c2": 0.35,
						"c3": 0.679,
						"c4": 0.7
					},
					{ "time": 0.9667, "x": 15.97, "y": 1.65, "curve": 0.382, "c2": 0.58, "c3": 0.731 },
					{ "time": 1.1, "x": 16.49, "y": 0.71, "curve": 0.302, "c3": 0.638, "c4": 0.36 },
					{
						"time": 1.3667,
						"x": 29.24,
						"y": 3.93,
						"curve": 0.309,
						"c2": 0.22,
						"c3": 0.645,
						"c4": 0.57
					},
					{ "time": 1.7, "x": 30.93, "y": 13.99, "curve": 0.361, "c2": 0.64, "c3": 0.697 },
					{ "time": 1.9667, "x": -21.27, "y": -3.25, "curve": 0.25, "c3": 0.75 },
					{ "time": 2.3333 }
				]
			},
			"blur bird5": {
				"rotate": [
					{ "curve": "stepped" },
					{ "time": 0.6667 },
					{ "time": 0.8, "angle": -17.54 },
					{ "time": 0.9, "curve": "stepped" },
					{ "time": 1.2333 },
					{ "time": 1.3667, "angle": -17.54 },
					{ "time": 1.4667, "curve": "stepped" },
					{ "time": 1.8333 },
					{ "time": 1.9333, "angle": -17.54 },
					{ "time": 2.0333, "curve": "stepped" },
					{ "time": 2.3333 }
				]
			},
			"blur bird4": {
				"rotate": [
					{ "curve": "stepped" },
					{ "time": 0.6667 },
					{ "time": 0.8, "angle": 16.71 },
					{ "time": 0.9, "curve": "stepped" },
					{ "time": 1.3 },
					{ "time": 1.4, "angle": 16.71 },
					{ "time": 1.5, "curve": "stepped" },
					{ "time": 1.8 },
					{ "time": 1.9, "angle": 16.71 },
					{ "time": 2.0333, "curve": "stepped" },
					{ "time": 2.3333 }
				]
			},
			"blur bird3": {
				"rotate": [
					{ "curve": "stepped" },
					{ "time": 0.3, "curve": 0.25, "c3": 0.75 },
					{ "time": 0.6, "angle": 14.72, "curve": "stepped" },
					{ "time": 0.8, "angle": 14.72, "curve": "stepped" },
					{ "time": 1.1, "angle": 14.72, "curve": 0.25, "c3": 0.75 },
					{ "time": 1.4333, "angle": -7.03, "curve": 0.25, "c3": 0.75 },
					{ "time": 2.3333 }
				]
			},
			"blur bird7": {
				"rotate": [
					{ "curve": 0.25, "c3": 0.75 },
					{ "time": 0.4667, "angle": 12.86, "curve": 0.25, "c3": 0.75 },
					{ "time": 0.9, "angle": -4.26, "curve": 0.25, "c3": 0.75 },
					{ "time": 1.3, "angle": 6.58, "curve": 0.25, "c3": 0.75 },
					{ "time": 1.6333, "angle": -5.13, "curve": 0.25, "c3": 0.75 },
					{ "time": 1.9333, "angle": 9.76, "curve": 0.25, "c3": 0.75 },
					{ "time": 2.3333 }
				]
			},
			"blur bird6": {
				"rotate": [
					{ "curve": 0.25, "c3": 0.75 },
					{ "time": 0.4667, "angle": -12.23, "curve": 0.25, "c3": 0.75 },
					{ "time": 0.9, "angle": 12.83, "curve": 0.25, "c3": 0.75 },
					{ "time": 1.3, "angle": -6.57, "curve": 0.25, "c3": 0.75 },
					{ "time": 1.6333, "angle": 12.85, "curve": 0.25, "c3": 0.75 },
					{ "time": 1.9333, "angle": -8.46, "curve": 0.25, "c3": 0.75 },
					{ "time": 2.3333 }
				]
			},
			"yellow bird4": {
				"rotate": [
					{ "curve": "stepped" },
					{ "time": 0.3667 },
					{ "time": 0.5, "angle": -25 },
					{ "time": 0.5667, "curve": "stepped" },
					{ "time": 0.7667 },
					{ "time": 0.8333, "angle": -17.47 },
					{ "time": 0.9, "curve": "stepped" },
					{ "time": 1.4 },
					{ "time": 1.5, "angle": -35.48 },
					{ "time": 1.5667, "curve": "stepped" },
					{ "time": 1.8333 },
					{ "time": 1.9, "angle": -21.37 },
					{ "time": 1.9667 }
				]
			},
			"yellow bird5": {
				"rotate": [
					{ "curve": "stepped" },
					{ "time": 0.3667 },
					{ "time": 0.5, "angle": 19.95 },
					{ "time": 0.5667, "curve": "stepped" },
					{ "time": 0.7667 },
					{ "time": 0.8333, "angle": 27.28 },
					{ "time": 0.9, "curve": "stepped" },
					{ "time": 1.4 },
					{ "time": 1.5, "angle": 14.44 },
					{ "time": 1.5667, "curve": "stepped" },
					{ "time": 1.8333 },
					{ "time": 1.9, "angle": 16.88 },
					{ "time": 1.9667 }
				]
			},
			"yellow bird7": {
				"rotate": [
					{},
					{ "time": 0.2667, "angle": -15.55 },
					{ "time": 0.6667, "angle": 19.73 },
					{ "time": 0.9667, "angle": 9.79 },
					{ "time": 1.2333, "angle": -8.76 },
					{ "time": 1.7, "angle": 15.57 },
					{ "time": 2.1, "angle": -5.61 },
					{ "time": 2.3333 }
				]
			},
			"yellow bird6": {
				"rotate": [
					{},
					{ "time": 0.2667, "angle": 14.49 },
					{ "time": 0.6667, "angle": -16.57 },
					{ "time": 0.9667, "angle": -2.82 },
					{ "time": 1.2333, "angle": -8.76 },
					{ "time": 1.7, "angle": 15.57 },
					{ "time": 2.1, "angle": -5.61 },
					{ "time": 2.3333 }
				]
			},
			"casc": {
				"rotate": [
					{ "curve": 0.25, "c3": 0.75 },
					{ "time": 0.6, "angle": -2.41, "curve": 0.25, "c3": 0.75 },
					{ "time": 1.1, "angle": 3.26, "curve": 0.25, "c3": 0.75 },
					{ "time": 1.4, "angle": -2.3, "curve": 0.25, "c3": 0.75 },
					{ "time": 1.7, "angle": 0.54, "curve": 0.25, "c3": 0.75 },
					{ "time": 2.0333, "angle": 2.62, "curve": 0.25, "c3": 0.75 },
					{ "time": 2.3333 }
				],
				"translate": [
					{ "curve": 0.257, "c3": 0.619, "c4": 0.46 },
					{
						"time": 1.1,
						"x": 8.69,
						"y": 0.09,
						"curve": 0.337,
						"c2": 0.35,
						"c3": 0.69,
						"c4": 0.74
					},
					{ "time": 1.8333, "x": -6.2, "y": -0.76, "curve": 0.378, "c2": 0.6, "c3": 0.722 },
					{ "time": 2.3333 }
				]
			},
			"r_pupil": {
				"translate": [
					{ "curve": "stepped" },
					{ "time": 0.2 },
					{ "time": 0.3, "x": -21.57 },
					{ "time": 0.3667, "x": -17.19, "curve": "stepped" },
					{ "time": 0.6333, "x": -17.19 },
					{ "time": 0.7, "x": 10.78, "y": 11.8 },
					{ "time": 0.7333, "x": 11.12, "y": 10.11, "curve": "stepped" },
					{ "time": 1.1667, "x": 11.12, "y": 10.11 },
					{ "time": 1.2333, "x": -2.58, "y": 4.47, "curve": "stepped" },
					{ "time": 1.4, "x": -2.58, "y": 4.47 },
					{ "time": 1.4667, "x": -17.27, "y": 4.92, "curve": "stepped" },
					{ "time": 1.7, "x": -17.27, "y": 4.92 },
					{ "time": 1.7667, "x": 9.98, "y": 4.92 }
				],
				"scale": [
					{ "time": 1.2333 },
					{ "time": 1.5, "x": 1.154, "y": 1.154 },
					{ "time": 2, "x": 1.724, "y": 1.724 },
					{ "time": 2.0667 }
				]
			},
			"l_pupil": {
				"translate": [
					{ "curve": "stepped" },
					{ "time": 0.2 },
					{ "time": 0.3, "x": -21.57 },
					{ "time": 0.3667, "x": -17.19, "curve": "stepped" },
					{ "time": 0.6333, "x": -17.19 },
					{ "time": 0.7, "x": 10.78, "y": 11.8 },
					{ "time": 0.7333, "x": 11.12, "y": 10.11, "curve": "stepped" },
					{ "time": 1.1667, "x": 11.12, "y": 10.11 },
					{ "time": 1.2333, "x": -2.58, "y": 4.47, "curve": "stepped" },
					{ "time": 1.4, "x": -2.58, "y": 4.47 },
					{ "time": 1.4667, "x": -17.27, "y": 4.92, "curve": "stepped" },
					{ "time": 1.7, "x": -17.27, "y": 4.92 },
					{ "time": 1.7667, "x": 9.98, "y": 4.92 }
				],
				"scale": [
					{ "time": 1.2333 },
					{ "time": 1.5, "x": 1.154, "y": 1.154 },
					{ "time": 2, "x": 1.724, "y": 1.724 },
					{ "time": 2.0667 }
				]
			},
			"r_eyebrow": {
				"translate": [
					{},
					{ "time": 0.6, "x": -4.9, "y": 14.69 },
					{ "time": 1.1667, "x": -2.47, "y": 11.5 },
					{ "time": 1.3333, "x": -1.92, "y": 31.92 },
					{ "time": 1.6, "x": -0.11, "y": 29.21 },
					{ "time": 1.8, "x": -0.38, "y": -1.43 },
					{ "time": 2.3333 }
				]
			},
			"l_eyebrow": {
				"translate": [
					{},
					{ "time": 0.6, "x": -4.9, "y": 14.69 },
					{ "time": 1.1667, "x": -2.47, "y": 11.5 },
					{ "time": 1.3333, "x": -1.92, "y": 31.92 },
					{ "time": 1.6, "x": -0.11, "y": 29.21 },
					{ "time": 1.8, "x": -0.38, "y": -1.43 },
					{ "time": 2.3333 }
				]
			},
			"chin": {
				"translate": [
					{ "curve": "stepped" },
					{ "time": 2.3333 }
				]
			},
			"automat_main": {
				"rotate": [
					{},
					{ "time": 0.6667, "angle": 20.02, "curve": "stepped" },
					{ "time": 1.1667, "angle": 20.02 },
					{ "time": 1.3667, "angle": 9.28 },
					{ "time": 1.5333, "angle": 7.26 },
					{ "time": 1.6667, "angle": 20.02 },
					{ "time": 2.3333 }
				],
				"translate": [
					{ "curve": 0.25, "c3": 0.75 },
					{ "time": 0.6667, "x": -1.57, "y": 38.25, "curve": 0.253, "c3": 0.621, "c4": 0.48 },
					{
						"time": 0.7333,
						"x": 42.52,
						"y": 56.93,
						"curve": 0.335,
						"c2": 0.34,
						"c3": 0.674,
						"c4": 0.69
					},
					{
						"time": 0.8,
						"x": -29.07,
						"y": 50.02,
						"curve": 0.345,
						"c2": 0.37,
						"c3": 0.681,
						"c4": 0.72
					},
					{
						"time": 0.8667,
						"x": 45.2,
						"y": 57.58,
						"curve": 0.355,
						"c2": 0.44,
						"c3": 0.691,
						"c4": 0.78
					},
					{ "time": 0.9333, "x": 65.22, "y": 71.05, "curve": 0.359, "c2": 0.64, "c3": 0.694 },
					{ "time": 1, "x": 18.34, "y": 75.28, "curve": 0.324, "c3": 0.657, "c4": 0.34 },
					{
						"time": 1.2667,
						"x": 5.96,
						"y": 59.37,
						"curve": 0.327,
						"c2": 0.25,
						"c3": 0.66,
						"c4": 0.58
					},
					{
						"time": 1.4667,
						"x": -6.66,
						"y": 53.49,
						"curve": 0.332,
						"c2": 0.32,
						"c3": 0.666,
						"c4": 0.66
					},
					{
						"time": 1.5,
						"x": -3.01,
						"y": 56.68,
						"curve": 0.328,
						"c2": 0.29,
						"c3": 0.662,
						"c4": 0.62
					},
					{ "time": 1.6667, "x": 18.34, "y": 75.28, "curve": 0.311, "c3": 0.645, "c4": 0.35 },
					{
						"time": 1.7333,
						"x": 79.19,
						"y": 79.34,
						"curve": 0.303,
						"c2": 0.18,
						"c3": 0.641,
						"c4": 0.54
					},
					{ "time": 1.8, "x": 18.34, "y": 75.28, "curve": 0.311, "c3": 0.645, "c4": 0.35 },
					{ "time": 1.9, "x": 21.4, "y": 55.17, "curve": 0.376, "c2": 0.51, "c3": 0.749 },
					{ "time": 2.3333 }
				]
			},
			"automat_handle": {
				"rotate": [
					{ "curve": 0.25, "c3": 0.75 },
					{ "time": 0.8, "angle": 11.06, "curve": 0.278, "c3": 0.622, "c4": 0.4 },
					{ "time": 0.9667, "angle": 3.77, "curve": 0.312, "c2": 0.27, "c3": 0.688, "c4": 0.73 },
					{ "time": 1.3333, "angle": 8.12, "curve": 0.378, "c2": 0.6, "c3": 0.722 },
					{ "time": 1.5, "angle": -1.25, "curve": 0.251, "c3": 0.623, "c4": 0.49 },
					{ "time": 1.9, "angle": -2.69, "curve": 0.373, "c2": 0.49, "c3": 0.751 },
					{ "time": 2.3333 }
				]
			},
			"hair": {
				"translate": [
					{},
					{ "time": 0.9667, "x": -6.11, "y": 1.31 },
					{ "time": 1.5, "x": 2.67, "y": 0.91 },
					{ "time": 2.3333 }
				]
			},
			"automat1": {
				"rotate": [
					{ "curve": 0.251, "c3": 0.623, "c4": 0.49 },
					{ "time": 0.4, "angle": -4.7, "curve": 0.373, "c2": 0.49, "c3": 0.751 },
					{ "time": 0.8333, "angle": 1.89, "curve": "stepped" },
					{ "time": 0.9, "angle": 1.89, "curve": 0.266, "c3": 0.618, "c4": 0.42 },
					{ "time": 1.1667, "angle": 3.53, "curve": 0.33, "c2": 0.32, "c3": 0.664, "c4": 0.66 },
					{ "time": 1.3, "angle": 8.76, "curve": 0.329, "c2": 0.32, "c3": 0.664, "c4": 0.66 },
					{ "time": 1.5667, "angle": 1.37, "curve": 0.333, "c2": 0.33, "c3": 0.667, "c4": 0.67 },
					{ "time": 1.8667, "angle": 2.18, "curve": 0.25, "c3": 0.75 },
					{ "time": 2.3333 }
				],
				"translate": [
					{}
				],
				"scale": [
					{ "time": 0.7667 },
					{ "time": 0.8333, "x": 0.845, "y": 1.05 },
					{ "time": 0.8667, "curve": "stepped" },
					{ "time": 0.9, "curve": "stepped" },
					{ "time": 1 },
					{ "time": 1.0667, "x": 0.845, "y": 1.05 },
					{ "time": 1.1333, "curve": "stepped" },
					{ "time": 1.7667 },
					{ "time": 1.8333, "x": 0.845, "y": 1.05 },
					{ "time": 1.9 }
				]
			},
			"l_forearm": {
				"translate": [
					{ "time": 0.2667, "x": -0.62, "y": -2.4 }
				]
			},
			"blur bird": {
				"rotate": [
					{ "time": 0.7667 },
					{ "time": 0.8333, "angle": -5.12 },
					{ "time": 0.9, "angle": 11.27 },
					{ "time": 0.9667 },
					{ "time": 1.0333, "angle": -5.12 },
					{ "time": 1.1, "angle": 11.27 },
					{ "time": 1.1667, "curve": "stepped" },
					{ "time": 1.8333 },
					{ "time": 1.9, "angle": -5.12 },
					{ "time": 1.9667, "angle": 11.27 },
					{ "time": 2.0333 }
				],
				"translate": [
					{},
					{ "time": 0.6333, "x": -3.69, "y": -3.94 },
					{ "time": 1.0333, "x": 3.78, "y": 0.68 },
					{ "time": 1.3333, "x": -3.62, "y": 1.37 },
					{ "time": 1.5333, "x": 3.18, "y": 1.3 },
					{ "time": 1.7667, "x": -2.8, "y": -0.02 },
					{ "time": 1.9333, "x": 3.53, "y": -0.07 },
					{ "time": 2.3333 }
				]
			},
			"yellow bird": {
				"rotate": [
					{ "time": 0.8 },
					{ "time": 0.8667, "angle": -5.12 },
					{ "time": 0.9333, "angle": 11.27 },
					{ "time": 1 },
					{ "time": 1.0667, "angle": -5.12 },
					{ "time": 1.1333, "angle": 11.27 },
					{ "time": 1.2, "curve": "stepped" },
					{ "time": 1.8667 },
					{ "time": 1.9333, "angle": -5.12 },
					{ "time": 2, "angle": 11.27 },
					{ "time": 2.0667 }
				],
				"translate": [
					{},
					{ "time": 0.4333, "x": -3.69, "y": -3.94 },
					{ "time": 0.8333, "x": 3.78, "y": 0.68 },
					{ "time": 1.1333, "x": -3.62, "y": 1.37 },
					{ "time": 1.3333, "x": 3.18, "y": 1.3 },
					{ "time": 1.5667, "x": -2.8, "y": -0.02 },
					{ "time": 1.7333, "x": 3.53, "y": -0.07 },
					{ "time": 2.3333 }
				]
			},
			"mouth": {
				"rotate": [
					{ "curve": "stepped" },
					{ "time": 0.3667, "curve": "stepped" },
					{ "time": 2.3333 }
				],
				"translate": [
					{ "curve": "stepped" },
					{ "time": 0.3667, "curve": 0.25, "c3": 0.75 },
					{ "time": 0.6667, "x": -1.36, "y": 24.53, "curve": "stepped" },
					{ "time": 1.1667, "x": -1.36, "y": 24.53, "curve": 0.295, "c3": 0.633, "c4": 0.37 },
					{
						"time": 1.3333,
						"x": -15.34,
						"y": 24.52,
						"curve": 0.29,
						"c2": 0.19,
						"c3": 0.652,
						"c4": 0.62
					},
					{ "time": 1.8333, "x": -13.39, "y": 23.1, "curve": 0.38, "c2": 0.53, "c3": 0.745 },
					{ "time": 2.3333 }
				],
				"scale": [
					{ "curve": "stepped" },
					{ "time": 0.3667, "curve": 0.25, "c3": 0.75 },
					{ "time": 0.6667, "y": 0.468, "curve": "stepped" },
					{ "time": 1.1667, "y": 0.468, "curve": "stepped" },
					{ "time": 1.5667, "y": 0.468, "curve": 0.25, "c3": 0.75 },
					{ "time": 2.3333 }
				]
			},
			"fat": {
				"translate": [
					{ "x": 22.65, "y": -2.52, "curve": "stepped" },
					{ "time": 0.7, "x": 22.65, "y": -2.52, "curve": 0.25, "c3": 0.75 },
					{ "time": 0.8333, "x": -10.07, "y": -2.52, "curve": 0.25, "c3": 0.75 },
					{ "time": 0.9667, "x": 22.65, "y": -2.52, "curve": 0.25, "c3": 0.75 },
					{ "time": 1.1, "x": -10.07, "y": -2.52, "curve": 0.25, "c3": 0.75 },
					{ "time": 1.2333, "x": 22.65, "y": -2.52, "curve": "stepped" },
					{ "time": 1.8667, "x": 22.65, "y": -2.52, "curve": 0.25, "c3": 0.75 },
					{ "time": 2, "x": -10.07, "y": -2.52, "curve": 0.25, "c3": 0.75 },
					{ "time": 2.1333, "x": 22.65, "y": -2.52, "curve": "stepped" },
					{ "time": 2.3333, "x": 22.65, "y": -2.52 }
				]
			},
			"r_ball_target": {
				"translate": [
					{ "x": -65.33 }
				]
			}
		}
	},
	"idle": {
		"slots": {
			"l_pupil": {
				"color": [
					{ "time": 2.5333, "color": "ffffffff" }
				]
			}
		},
		"bones": {
			"hip": {
				"rotate": [
					{ "curve": "stepped" },
					{ "time": 2.6667, "curve": "stepped" },
					{ "time": 5.3333 }
				],
				"translate": [
					{ "y": -27.81, "curve": 0.25, "c3": 0.75 },
					{ "time": 1, "x": 6.59, "y": -49.24, "curve": 0.25, "c3": 0.75 },
					{ "time": 2.1667, "x": -1.65, "y": -7.21, "curve": 0.25, "c3": 0.75 },
					{ "time": 2.6667, "y": -27.81, "curve": 0.25, "c3": 0.75 },
					{ "time": 3.6667, "x": 6.59, "y": -49.24, "curve": 0.25, "c3": 0.75 },
					{ "time": 4.8333, "x": -1.65, "y": -7.21, "curve": 0.25, "c3": 0.75 },
					{ "time": 5.3333, "y": -27.81 }
				]
			},
			"head": {
				"rotate": [
					{ "curve": "stepped" },
					{ "time": 2.6667, "curve": "stepped" },
					{ "time": 5.3333 }
				],
				"translate": [
					{ "curve": 0.25, "c3": 0.75 },
					{ "time": 0.7667, "x": 6.72, "y": 0.97, "curve": 0.25, "c3": 0.75 },
					{ "time": 1.7333, "x": -3.47, "y": -2.73, "curve": 0.25, "c3": 0.75 },
					{ "time": 2.6667, "curve": "stepped" },
					{ "time": 2.8333, "curve": 0.318, "c2": 0.23, "c3": 0.653, "c4": 0.57 },
					{
						"time": 3,
						"x": -10.09,
						"y": 0.22,
						"curve": 0.32,
						"c2": 0.27,
						"c3": 0.654,
						"c4": 0.61
					},
					{ "time": 3.2, "curve": 0.323, "c2": 0.3, "c3": 0.657, "c4": 0.63 },
					{
						"time": 3.4,
						"x": -6.76,
						"y": -1.54,
						"curve": 0.327,
						"c2": 0.31,
						"c3": 0.661,
						"c4": 0.65
					},
					{ "time": 3.5667, "curve": 0.329, "c2": 0.32, "c3": 0.663, "c4": 0.65 },
					{
						"time": 3.7667,
						"x": -5.1,
						"y": -2.41,
						"curve": 0.331,
						"c2": 0.33,
						"c3": 0.665,
						"c4": 0.66
					},
					{ "time": 3.9333, "curve": 0.333, "c2": 0.33, "c3": 0.667, "c4": 0.67 },
					{
						"time": 4.1,
						"x": -5.89,
						"y": 0.13,
						"curve": 0.335,
						"c2": 0.34,
						"c3": 0.67,
						"c4": 0.68
					},
					{ "time": 4.3, "curve": 0.337, "c2": 0.35, "c3": 0.671, "c4": 0.68 },
					{
						"time": 4.4667,
						"x": -5.9,
						"y": -0.71,
						"curve": 0.339,
						"c2": 0.35,
						"c3": 0.673,
						"c4": 0.69
					},
					{ "time": 4.6333, "curve": 0.341, "c2": 0.36, "c3": 0.675, "c4": 0.7 },
					{
						"time": 4.8,
						"x": -5.98,
						"y": -4.08,
						"curve": 0.344,
						"c2": 0.38,
						"c3": 0.678,
						"c4": 0.72
					},
					{ "time": 4.9667, "curve": "stepped" },
					{ "time": 5.3333 }
				]
			},
			"head1": {
				"rotate": [
					{ "curve": "stepped" },
					{ "time": 2.6667, "curve": "stepped" },
					{ "time": 5.3333 }
				],
				"translate": [
					{ "curve": 0.25, "c3": 0.75 },
					{ "time": 0.6333, "x": 16.49, "y": 0.71, "curve": "stepped" },
					{ "time": 1.0333, "x": 16.49, "y": 0.71, "curve": 0.25, "c3": 0.75 },
					{ "time": 2.2, "x": -21.27, "y": -3.25, "curve": 0.25, "c3": 0.75 },
					{ "time": 2.6667, "curve": "stepped" },
					{ "time": 2.7667, "curve": "stepped" },
					{ "time": 2.9333, "curve": 0.325, "c2": 0.27, "c3": 0.658, "c4": 0.6 },
					{
						"time": 3.1333,
						"x": -17.21,
						"y": 0.04,
						"curve": 0.327,
						"c2": 0.3,
						"c3": 0.661,
						"c4": 0.63
					},
					{ "time": 3.3, "curve": 0.328, "c2": 0.31, "c3": 0.662, "c4": 0.65 },
					{
						"time": 3.4667,
						"x": -17.2,
						"y": 0.04,
						"curve": 0.328,
						"c2": 0.32,
						"c3": 0.662,
						"c4": 0.65
					},
					{ "time": 3.6667, "curve": 0.331, "c2": 0.32, "c3": 0.664, "c4": 0.66 },
					{
						"time": 3.8667,
						"x": -19.56,
						"y": 0.04,
						"curve": 0.332,
						"c2": 0.33,
						"c3": 0.665,
						"c4": 0.66
					},
					{ "time": 4.0333, "curve": 0.333, "c2": 0.33, "c3": 0.667, "c4": 0.67 },
					{
						"time": 4.2,
						"x": -25.12,
						"y": 0.05,
						"curve": 0.334,
						"c2": 0.33,
						"c3": 0.667,
						"c4": 0.67
					},
					{ "time": 4.4, "curve": 0.335, "c2": 0.34, "c3": 0.669, "c4": 0.67 },
					{
						"time": 4.5667,
						"x": -30.73,
						"y": 0.06,
						"curve": 0.336,
						"c2": 0.34,
						"c3": 0.669,
						"c4": 0.67
					},
					{ "time": 4.7333, "curve": 0.337, "c2": 0.35, "c3": 0.671, "c4": 0.68 },
					{
						"time": 4.9,
						"x": -29.96,
						"y": 0.06,
						"curve": 0.338,
						"c2": 0.35,
						"c3": 0.671,
						"c4": 0.68
					},
					{ "time": 5.0667, "curve": 0.348, "c2": 0.43, "c3": 0.682, "c4": 0.77 },
					{ "time": 5.2, "x": -17.57, "y": 0.04, "curve": 0.353, "c2": 0.65, "c3": 0.687 },
					{ "time": 5.3333 }
				]
			},
			"blur bird5": {
				"rotate": [
					{ "curve": "stepped" },
					{ "time": 0.6 },
					{ "time": 0.7333, "angle": -17.54 },
					{ "time": 0.8667, "curve": "stepped" },
					{ "time": 1.3 },
					{ "time": 1.4333, "angle": -17.54 },
					{ "time": 1.5667, "curve": "stepped" },
					{ "time": 2.0333 },
					{ "time": 2.1667, "angle": -17.54 },
					{ "time": 2.3, "curve": "stepped" },
					{ "time": 2.6667, "curve": "stepped" },
					{ "time": 3.2667 },
					{ "time": 3.4, "angle": -17.54 },
					{ "time": 3.5333, "curve": "stepped" },
					{ "time": 3.9667 },
					{ "time": 4.1, "angle": -17.54 },
					{ "time": 4.2333, "curve": "stepped" },
					{ "time": 4.7 },
					{ "time": 4.8333, "angle": -17.54 },
					{ "time": 4.9667, "curve": "stepped" },
					{ "time": 5.3333 }
				]
			},
			"blur bird4": {
				"rotate": [
					{ "curve": "stepped" },
					{ "time": 0.6 },
					{ "time": 0.7333, "angle": 16.71 },
					{ "time": 0.8667, "curve": "stepped" },
					{ "time": 1.3333 },
					{ "time": 1.4667, "angle": 16.71 },
					{ "time": 1.6, "curve": "stepped" },
					{ "time": 2 },
					{ "time": 2.1333, "angle": 16.71 },
					{ "time": 2.2667, "curve": "stepped" },
					{ "time": 2.6667, "curve": "stepped" },
					{ "time": 3.2667 },
					{ "time": 3.4, "angle": 16.71 },
					{ "time": 3.5333, "curve": "stepped" },
					{ "time": 4 },
					{ "time": 4.1333, "angle": 16.71 },
					{ "time": 4.2667, "curve": "stepped" },
					{ "time": 4.6667 },
					{ "time": 4.8, "angle": 16.71 },
					{ "time": 4.9333, "curve": "stepped" },
					{ "time": 5.3333 }
				]
			},
			"blur bird3": {
				"rotate": [
					{ "curve": "stepped" },
					{ "time": 0.2667, "curve": 0.25, "c3": 0.75 },
					{ "time": 0.5333, "angle": 14.72, "curve": "stepped" },
					{ "time": 0.7, "angle": 14.72, "curve": "stepped" },
					{ "time": 1.1333, "angle": 14.72, "curve": 0.25, "c3": 0.75 },
					{ "time": 1.5333, "angle": -7.03, "curve": 0.25, "c3": 0.75 },
					{ "time": 2.6667, "curve": "stepped" },
					{ "time": 2.9333, "curve": 0.25, "c3": 0.75 },
					{ "time": 3.2, "angle": 14.72, "curve": "stepped" },
					{ "time": 3.3667, "angle": 14.72, "curve": "stepped" },
					{ "time": 3.8, "angle": 14.72, "curve": 0.25, "c3": 0.75 },
					{ "time": 4.2, "angle": -7.03, "curve": 0.25, "c3": 0.75 },
					{ "time": 5.3333 }
				]
			},
			"blur bird7": {
				"rotate": [
					{ "curve": 0.25, "c3": 0.75 },
					{ "time": 0.4, "angle": 12.86, "curve": 0.25, "c3": 0.75 },
					{ "time": 0.8667, "angle": -4.26, "curve": 0.25, "c3": 0.75 },
					{ "time": 1.3333, "angle": 6.58, "curve": 0.25, "c3": 0.75 },
					{ "time": 1.7333, "angle": -5.13, "curve": 0.25, "c3": 0.75 },
					{ "time": 2.1667, "angle": 9.76, "curve": 0.25, "c3": 0.75 },
					{ "time": 2.6667, "curve": 0.25, "c3": 0.75 },
					{ "time": 3.0667, "angle": 12.86, "curve": 0.25, "c3": 0.75 },
					{ "time": 3.5333, "angle": -4.26, "curve": 0.25, "c3": 0.75 },
					{ "time": 4, "angle": 6.58, "curve": 0.25, "c3": 0.75 },
					{ "time": 4.4, "angle": -5.13, "curve": 0.25, "c3": 0.75 },
					{ "time": 4.8333, "angle": 9.76, "curve": 0.25, "c3": 0.75 },
					{ "time": 5.3333 }
				]
			},
			"blur bird6": {
				"rotate": [
					{ "curve": 0.25, "c3": 0.75 },
					{ "time": 0.4, "angle": -12.23, "curve": 0.25, "c3": 0.75 },
					{ "time": 0.8667, "angle": 12.83, "curve": 0.25, "c3": 0.75 },
					{ "time": 1.3333, "angle": -6.57, "curve": 0.25, "c3": 0.75 },
					{ "time": 1.7333, "angle": 12.85, "curve": 0.25, "c3": 0.75 },
					{ "time": 2.1667, "angle": -8.46, "curve": 0.25, "c3": 0.75 },
					{ "time": 2.6667, "curve": 0.25, "c3": 0.75 },
					{ "time": 3.0667, "angle": -12.23, "curve": 0.25, "c3": 0.75 },
					{ "time": 3.5333, "angle": 12.83, "curve": 0.25, "c3": 0.75 },
					{ "time": 4, "angle": -6.57, "curve": 0.25, "c3": 0.75 },
					{ "time": 4.4, "angle": 12.85, "curve": 0.25, "c3": 0.75 },
					{ "time": 4.8333, "angle": -8.46, "curve": 0.25, "c3": 0.75 },
					{ "time": 5.3333 }
				]
			},
			"yellow bird4": {
				"rotate": [
					{ "curve": "stepped" },
					{ "time": 0.3333 },
					{ "time": 0.4333, "angle": -25 },
					{ "time": 0.5, "curve": "stepped" },
					{ "time": 0.6667 },
					{ "time": 0.7667, "angle": -17.47 },
					{ "time": 0.8333, "curve": "stepped" },
					{ "time": 1.5 },
					{ "time": 1.6, "angle": -35.48 },
					{ "time": 1.6667, "curve": "stepped" },
					{ "time": 2.0333 },
					{ "time": 2.1333, "angle": -21.37 },
					{ "time": 2.2, "curve": "stepped" },
					{ "time": 2.6667, "curve": "stepped" },
					{ "time": 3 },
					{ "time": 3.1, "angle": -25 },
					{ "time": 3.1667, "curve": "stepped" },
					{ "time": 3.3333 },
					{ "time": 3.4333, "angle": -17.47 },
					{ "time": 3.5, "curve": "stepped" },
					{ "time": 4.1667 },
					{ "time": 4.2667, "angle": -35.48 },
					{ "time": 4.3333, "curve": "stepped" },
					{ "time": 4.7 },
					{ "time": 4.8, "angle": -21.37 },
					{ "time": 4.8667, "curve": "stepped" },
					{ "time": 5.3333 }
				]
			},
			"yellow bird5": {
				"rotate": [
					{ "curve": "stepped" },
					{ "time": 0.3333 },
					{ "time": 0.4333, "angle": 19.95 },
					{ "time": 0.5, "curve": "stepped" },
					{ "time": 0.6667 },
					{ "time": 0.7667, "angle": 27.28 },
					{ "time": 0.8333, "curve": "stepped" },
					{ "time": 1.5 },
					{ "time": 1.6, "angle": 14.44 },
					{ "time": 1.6667, "curve": "stepped" },
					{ "time": 2.0333 },
					{ "time": 2.1333, "angle": 16.88 },
					{ "time": 2.2, "curve": "stepped" },
					{ "time": 2.6667, "curve": "stepped" },
					{ "time": 3 },
					{ "time": 3.1, "angle": 19.95 },
					{ "time": 3.1667, "curve": "stepped" },
					{ "time": 3.3333 },
					{ "time": 3.4333, "angle": 27.28 },
					{ "time": 3.5, "curve": "stepped" },
					{ "time": 4.1667 },
					{ "time": 4.2667, "angle": 14.44 },
					{ "time": 4.3333, "curve": "stepped" },
					{ "time": 4.7 },
					{ "time": 4.8, "angle": 16.88 },
					{ "time": 4.8667, "curve": "stepped" },
					{ "time": 5.3333 }
				]
			},
			"yellow bird7": {
				"rotate": [
					{},
					{ "time": 0.2333, "angle": -15.55 },
					{ "time": 0.5667, "angle": 19.73 },
					{ "time": 0.9667, "angle": 9.79 },
					{ "time": 1.2667, "angle": -8.76 },
					{ "time": 1.9, "angle": 15.57 },
					{ "time": 2.3667, "angle": -5.61 },
					{ "time": 2.6667 },
					{ "time": 2.9, "angle": -15.55 },
					{ "time": 3.2333, "angle": 19.73 },
					{ "time": 3.6333, "angle": 9.79 },
					{ "time": 3.9333, "angle": -8.76 },
					{ "time": 4.5667, "angle": 15.57 },
					{ "time": 5.0333, "angle": -5.61 },
					{ "time": 5.3333 }
				]
			},
			"yellow bird6": {
				"rotate": [
					{},
					{ "time": 0.2333, "angle": 14.49 },
					{ "time": 0.5667, "angle": -16.57 },
					{ "time": 0.9667, "angle": -2.82 },
					{ "time": 1.2667, "angle": -8.76 },
					{ "time": 1.9, "angle": 15.57 },
					{ "time": 2.3667, "angle": -5.61 },
					{ "time": 2.6667 },
					{ "time": 2.9, "angle": 14.49 },
					{ "time": 3.2333, "angle": -16.57 },
					{ "time": 3.6333, "angle": -2.82 },
					{ "time": 3.9333, "angle": -8.76 },
					{ "time": 4.5667, "angle": 15.57 },
					{ "time": 5.0333, "angle": -5.61 },
					{ "time": 5.3333 }
				]
			},
			"casc": {
				"rotate": [
					{ "curve": 0.25, "c3": 0.75 },
					{ "time": 0.5333, "angle": -2.41, "curve": 0.25, "c3": 0.75 },
					{ "time": 1.1, "angle": 3.26, "curve": 0.25, "c3": 0.75 },
					{ "time": 1.4667, "angle": -2.3, "curve": 0.25, "c3": 0.75 },
					{ "time": 1.9, "angle": 0.54, "curve": 0.25, "c3": 0.75 },
					{ "time": 2.4, "angle": 1.75, "curve": 0.25, "c3": 0.75 },
					{ "time": 2.6667, "curve": "stepped" },
					{ "time": 2.8333, "curve": 0.316, "c2": 0.22, "c3": 0.65, "c4": 0.56 },
					{ "time": 3.0333, "angle": -2.43, "curve": 0.322, "c2": 0.28, "c3": 0.656, "c4": 0.62 },
					{ "time": 3.2, "curve": 0.323, "c2": 0.3, "c3": 0.657, "c4": 0.63 },
					{ "time": 3.4, "angle": -3.39, "curve": 0.327, "c2": 0.31, "c3": 0.661, "c4": 0.65 },
					{ "time": 3.5667, "curve": 0.329, "c2": 0.32, "c3": 0.663, "c4": 0.65 },
					{ "time": 3.7667, "angle": -3.83, "curve": 0.331, "c2": 0.33, "c3": 0.665, "c4": 0.66 },
					{ "time": 3.9333, "curve": 0.333, "c2": 0.33, "c3": 0.668, "c4": 0.67 },
					{ "time": 4.1333, "angle": -3.05, "curve": 0.335, "c2": 0.34, "c3": 0.669, "c4": 0.67 },
					{ "time": 4.3, "curve": 0.337, "c2": 0.35, "c3": 0.671, "c4": 0.68 },
					{ "time": 4.4667, "angle": -2.2, "curve": 0.339, "c2": 0.35, "c3": 0.673, "c4": 0.69 },
					{ "time": 4.6333, "curve": 0.341, "c2": 0.36, "c3": 0.675, "c4": 0.7 },
					{ "time": 4.8, "angle": -2.59, "curve": 0.344, "c2": 0.38, "c3": 0.678, "c4": 0.72 },
					{ "time": 4.9667, "curve": "stepped" },
					{ "time": 5.3333 }
				],
				"translate": [
					{ "curve": "stepped" },
					{ "time": 2.6667, "curve": "stepped" },
					{ "time": 2.8333, "curve": "stepped" },
					{ "time": 3.2, "curve": "stepped" },
					{ "time": 3.5667, "curve": "stepped" },
					{ "time": 3.9333, "curve": "stepped" },
					{ "time": 4.3, "curve": "stepped" },
					{ "time": 4.6333, "curve": "stepped" },
					{ "time": 4.9667, "curve": "stepped" },
					{ "time": 5.3333 }
				]
			},
			"r_pupil": {
				"rotate": [
					{ "angle": 0.1, "curve": "stepped" },
					{ "time": 2.4667, "angle": 0.1, "curve": "stepped" },
					{ "time": 5.3333, "angle": 0.1 }
				],
				"translate": [
					{ "curve": "stepped" },
					{ "time": 0.4667 },
					{ "time": 0.5333, "x": -21.57 },
					{ "time": 0.5667, "x": -17.19, "curve": "stepped" },
					{ "time": 0.9333, "x": -17.19 },
					{ "time": 1, "x": 10.78, "y": 11.8 },
					{ "time": 1.0333, "x": 11.12, "y": 10.11, "curve": "stepped" },
					{ "time": 1.6667, "x": 11.12, "y": 10.11 },
					{ "time": 1.7333, "x": 6.07, "y": -17.86 },
					{ "time": 1.7667, "x": 2.02, "y": -21.23, "curve": "stepped" },
					{ "time": 2.4667, "x": 2.02, "y": -21.23 },
					{ "time": 2.5667, "x": -6.87, "y": -2.82, "curve": "stepped" },
					{ "time": 5.3, "x": -6.87, "y": -2.82 },
					{ "time": 5.3333, "x": 2.02, "y": -7.5 }
				],
				"scale": [
					{ "time": 2.5667 },
					{ "time": 2.7333, "x": 1.434, "y": 1.434, "curve": "stepped" },
					{ "time": 3.3, "x": 1.434, "y": 1.434 },
					{ "time": 3.4333, "x": 2.069, "y": 2.069 },
					{ "time": 3.7667, "x": 2.03, "y": 2.03 },
					{ "time": 4, "x": 1.434, "y": 1.434, "curve": "stepped" },
					{ "time": 5.1, "x": 1.434, "y": 1.434 },
					{ "time": 5.3 }
				]
			},
			"l_pupil": {
				"rotate": [
					{ "angle": 0.1, "curve": "stepped" },
					{ "time": 2.4667, "angle": 0.1, "curve": "stepped" },
					{ "time": 5.3333, "angle": 0.1 }
				],
				"translate": [
					{ "curve": "stepped" },
					{ "time": 0.4667 },
					{ "time": 0.5333, "x": -21.57 },
					{ "time": 0.5667, "x": -17.19, "curve": "stepped" },
					{ "time": 0.9333, "x": -17.19 },
					{ "time": 1, "x": 10.78, "y": 11.8 },
					{ "time": 1.0333, "x": 11.12, "y": 10.11, "curve": "stepped" },
					{ "time": 1.6667, "x": 11.12, "y": 10.11 },
					{ "time": 1.7333, "x": 6.07, "y": -17.86 },
					{ "time": 1.7667, "x": 2.02, "y": -21.23, "curve": "stepped" },
					{ "time": 2.4667, "x": 2.02, "y": -21.23 },
					{ "time": 2.5667, "x": -6.87, "y": -2.82, "curve": "stepped" },
					{ "time": 5.3, "x": -6.87, "y": -2.82 },
					{ "time": 5.3333, "x": 2.02, "y": -7.5 }
				],
				"scale": [
					{ "time": 2.5667 },
					{ "time": 2.7333, "x": 1.434, "y": 1.434, "curve": "stepped" },
					{ "time": 3.3, "x": 1.434, "y": 1.434 },
					{ "time": 3.4333, "x": 2.069, "y": 2.069 },
					{ "time": 3.7667, "x": 2.03, "y": 2.03 },
					{ "time": 4, "x": 1.434, "y": 1.434, "curve": "stepped" },
					{ "time": 5.1, "x": 1.434, "y": 1.434 },
					{ "time": 5.3 }
				]
			},
			"r_eyebrow": {
				"translate": [
					{},
					{ "time": 0.5333, "x": -4.9, "y": 14.69 },
					{ "time": 1.2333, "x": -2.47, "y": 11.5 },
					{ "time": 1.9667, "x": -0.38, "y": -1.43 },
					{ "time": 2.6667 },
					{ "time": 2.8667, "x": -2, "y": 23.55 },
					{ "time": 5.3333 }
				]
			},
			"l_eyebrow": {
				"translate": [
					{},
					{ "time": 0.6, "x": -4.9, "y": 14.69 },
					{ "time": 1.3, "x": -2.47, "y": 11.5 },
					{ "time": 2.0333, "x": -0.38, "y": -1.43 },
					{ "time": 2.6667 },
					{ "time": 2.8667, "x": -2, "y": 23.55 },
					{ "time": 5.3333 }
				]
			},
			"chin": {
				"translate": [
					{ "curve": "stepped" },
					{ "time": 2.6667, "curve": "stepped" },
					{ "time": 5.3333 }
				]
			},
			"automat_main": {
				"translate": [
					{ "curve": 0.25, "c3": 0.75 },
					{ "time": 0.6, "y": 11.61, "curve": 0.25, "c3": 0.75 },
					{ "time": 1.4667, "x": 5.8, "y": -7.77, "curve": 0.25, "c3": 0.75 },
					{ "time": 2.6667, "curve": 0.308, "c3": 0.643, "c4": 0.35 },
					{ "time": 3.0667, "x": -8.46, "y": 50.76, "curve": 0.285, "c2": 0.15, "c3": 0.754 },
					{ "time": 5.3333 }
				]
			},
			"automat_handle": {
				"rotate": [
					{ "curve": 0.25, "c3": 0.75 },
					{ "time": 0.7333, "angle": 11.06, "curve": 0.25, "c3": 0.75 },
					{ "time": 1.6333, "angle": -1.25, "curve": 0.25, "c3": 0.75 },
					{ "time": 2.6667, "curve": 0.25, "c3": 0.75 },
					{ "time": 3.4, "angle": 11.06, "curve": 0.25, "c3": 0.75 },
					{ "time": 4.3, "angle": -1.25, "curve": 0.25, "c3": 0.75 },
					{ "time": 5.3333 }
				]
			},
			"automat1": {
				"rotate": [
					{ "curve": 0.251, "c3": 0.623, "c4": 0.49 },
					{ "time": 0.6333, "angle": 5.32, "curve": 0.379, "c2": 0.52, "c3": 0.747 },
					{ "time": 1.9, "angle": -4.7, "curve": 0.373, "c2": 0.49, "c3": 0.751 },
					{ "time": 2.6667, "curve": 0.251, "c3": 0.623, "c4": 0.49 },
					{ "time": 3.3, "angle": 5.32, "curve": 0.379, "c2": 0.52, "c3": 0.747 },
					{ "time": 4.5667, "angle": -4.7, "curve": 0.373, "c2": 0.49, "c3": 0.751 },
					{ "time": 5.3333 }
				]
			},
			"mouth": {
				"translate": [
					{ "curve": "stepped" },
					{ "time": 2.6667 },
					{ "time": 2.8333, "x": 3.64, "y": 2.92 },
					{ "time": 2.9333, "x": 5.1, "y": -0.73 },
					{ "time": 3.0333, "x": 2.19, "y": 8.02 },
					{ "time": 3.2, "x": 3.64, "y": 2.92 },
					{ "time": 3.3, "x": 5.1, "y": -0.73 },
					{ "time": 3.4, "x": 2.19, "y": 8.02 },
					{ "time": 3.5667, "x": 3.64, "y": 2.92 },
					{ "time": 3.6667, "x": 5.1, "y": -0.73 },
					{ "time": 3.7667, "x": 2.19, "y": 8.02 },
					{ "time": 3.9333, "x": 3.64, "y": 2.92 },
					{ "time": 4.0333, "x": 5.1, "y": -0.73 },
					{ "time": 4.1333, "x": 2.19, "y": 8.02 },
					{ "time": 4.3, "x": 3.64, "y": 2.92 },
					{ "time": 4.4, "x": 5.1, "y": -0.73 },
					{ "time": 4.5, "x": 2.19, "y": 8.02 },
					{ "time": 4.6333, "x": 3.64, "y": 2.92 },
					{ "time": 4.7333, "x": 5.1, "y": -0.73 },
					{ "time": 4.8333, "x": 2.19, "y": 8.02 },
					{ "time": 4.9667, "x": 3.64, "y": 2.92 },
					{ "time": 5.0667, "x": 5.1, "y": -0.73 },
					{ "time": 5.1667, "x": 2.19, "y": 8.02 },
					{ "time": 5.3333 }
				],
				"scale": [
					{},
					{ "time": 0.8, "y": 0.771 },
					{ "time": 2.1333, "x": 0.985, "y": 1.094 },
					{ "time": 2.6667 },
					{ "time": 2.8333, "x": 1.277, "y": 0.952 },
					{ "time": 3.0333, "x": 1.19, "y": 0.895 },
					{ "time": 3.2, "x": 1.277, "y": 0.952 },
					{ "time": 3.4, "x": 1.19, "y": 0.895 },
					{ "time": 3.5667, "x": 1.277, "y": 0.952 },
					{ "time": 3.7667, "x": 1.19, "y": 0.895 },
					{ "time": 3.9333, "x": 1.277, "y": 0.952 },
					{ "time": 4.1333, "x": 1.19, "y": 0.895 },
					{ "time": 4.3, "x": 1.277, "y": 0.952 },
					{ "time": 4.5, "x": 1.19, "y": 0.895 },
					{ "time": 4.6333, "x": 1.277, "y": 0.952 },
					{ "time": 4.8333, "x": 1.19, "y": 0.895 },
					{ "time": 4.9667, "x": 1.277, "y": 0.952 },
					{ "time": 5.1667, "x": 1.19, "y": 0.895 },
					{ "time": 5.3333 }
				]
			},
			"r_eye": {
				"scale": [
					{ "curve": "stepped" },
					{ "time": 2.6667 },
					{ "time": 2.8333, "y": 0.852 },
					{ "time": 3.1333, "y": 1.02, "curve": "stepped" },
					{ "time": 5.0667, "y": 1.02 },
					{ "time": 5.3333 }
				]
			},
			"l_eye": {
				"scale": [
					{ "curve": "stepped" },
					{ "time": 2.6667 },
					{ "time": 2.8333, "y": 0.852 },
					{ "time": 3.1333, "y": 1.02, "curve": "stepped" },
					{ "time": 5.0667, "y": 1.02 },
					{ "time": 5.3333 }
				]
			},
			"spine1": {
				"translate": [
					{ "time": 2.6667, "curve": "stepped" },
					{ "time": 2.8333, "curve": 0.318, "c2": 0.23, "c3": 0.653, "c4": 0.57 },
					{
						"time": 3,
						"x": 3.07,
						"y": -12.06,
						"curve": 0.32,
						"c2": 0.27,
						"c3": 0.654,
						"c4": 0.61
					},
					{ "time": 3.2, "curve": 0.323, "c2": 0.3, "c3": 0.657, "c4": 0.63 },
					{
						"time": 3.4,
						"x": 3.07,
						"y": -12.06,
						"curve": 0.32,
						"c2": 0.27,
						"c3": 0.654,
						"c4": 0.61
					},
					{ "time": 3.5667, "curve": 0.329, "c2": 0.32, "c3": 0.663, "c4": 0.65 },
					{
						"time": 3.7667,
						"x": 3.07,
						"y": -12.06,
						"curve": 0.32,
						"c2": 0.27,
						"c3": 0.654,
						"c4": 0.61
					},
					{ "time": 3.9333, "curve": 0.333, "c2": 0.33, "c3": 0.667, "c4": 0.67 },
					{
						"time": 4.1,
						"x": 3.07,
						"y": -12.06,
						"curve": 0.32,
						"c2": 0.27,
						"c3": 0.654,
						"c4": 0.61
					},
					{ "time": 4.3, "curve": 0.337, "c2": 0.35, "c3": 0.671, "c4": 0.68 },
					{
						"time": 4.4667,
						"x": 3.07,
						"y": -12.06,
						"curve": 0.32,
						"c2": 0.27,
						"c3": 0.654,
						"c4": 0.61
					},
					{ "time": 4.6333, "curve": 0.341, "c2": 0.36, "c3": 0.675, "c4": 0.7 },
					{
						"time": 4.8,
						"x": 3.07,
						"y": -12.06,
						"curve": 0.32,
						"c2": 0.27,
						"c3": 0.654,
						"c4": 0.61
					},
					{ "time": 4.9667, "curve": "stepped" },
					{ "time": 5.3333 }
				]
			},
			"r_ball_target": {
				"translate": [
					{ "x": -65.33 }
				]
			}
		}
	}
}
}